<?xml version="1.0" encoding="UTF-8"?>
<package packagerversion="1.9.4" version="2.0" xmlns="http://pear.php.net/dtd/package-2.0" xmlns:tasks="http://pear.php.net/dtd/tasks-1.0" xmlns:xsi="http://www.w3.org/2001/XMLSchema-instance" xsi:schemaLocation="http://pear.php.net/dtd/tasks-1.0 http://pear.php.net/dtd/tasks-1.0.xsd http://pear.php.net/dtd/package-2.0 http://pear.php.net/dtd/package-2.0.xsd">
 <name>protobuf</name>
 <channel>pecl.php.net</channel>
 <summary>Google&apos;s language-neutral, platform-neutral, extensible mechanism for serializing structured data.</summary>
 <description>https://developers.google.com/protocol-buffers/</description>
 <lead>
  <name>Bo Yang</name>
  <user>stanleycheung</user>
  <email>protobuf-opensource@google.com</email>
  <active>yes</active>
 </lead>
 <date>2017-12-06</date>
 <time>23:56:30</time>
 <version>
  <release>3.5.0.1</release>
  <api>3.5.0.1</api>
 </version>
 <stability>
  <release>stable</release>
  <api>stable</api>
 </stability>
 <license uri="https://opensource.org/licenses/BSD-3-Clause">3-Clause BSD License</license>
 <notes>
GA release.
 </notes>
 <contents>
  <dir baseinstalldir="/" name="/">
   <file baseinstalldir="/" md5sum="18cfcb78bffead86bc42aa822cc4e777" name="config.m4" role="src" />
   <file baseinstalldir="/" md5sum="e6ae37067825753f37c510e1cbbd2683" name="array.c" role="src" />
   <file baseinstalldir="/" md5sum="599cf9eddfc7f0bfdd7cb51d140619cd" name="def.c" role="src" />
   <file baseinstalldir="/" md5sum="ef99895d2c7a32d1f231be887cd6eab2" name="encode_decode.c" role="src" />
   <file baseinstalldir="/" md5sum="63f7ee94e7614504c79a6ee4eb6958a3" name="map.c" role="src" />
   <file baseinstalldir="/" md5sum="3e989060d07302c0490de1f874b465b3" name="message.c" role="src" />
   <file baseinstalldir="/" md5sum="25470c5f74d04218ef3d21481302316a" name="protobuf.c" role="src" />
   <file baseinstalldir="/" md5sum="a22efdaf30809a7e192eb11c7b26afd4" name="protobuf.h" role="src" />
   <file baseinstalldir="/" md5sum="4b93eccb240a5ddb0dc02ccd12f71d6c" name="storage.c" role="src" />
   <file baseinstalldir="/" md5sum="9bdda10fa94917580fcd16a6cbc6c372" name="type_check.c" role="src" />
   <file baseinstalldir="/" md5sum="0316d64938fa1afc1f77f040d41c7074" name="upb.c" role="src" />
   <file baseinstalldir="/" md5sum="698834d542bd03eff162d2b5640dc498" name="upb.h" role="src" />
   <file baseinstalldir="/" md5sum="03bd1157cce48d2c549a016d21025f8f" name="utf8.c" role="src" />
   <file baseinstalldir="/" md5sum="2efa1ba503d50e8d418054ceecd7bff8" name="utf8.h" role="src" />
   <file baseinstalldir="/" md5sum="35953c752efc9299b184f91bef540095" name="LICENSE" role="doc" />
  </dir>
 </contents>
 <dependencies>
  <required>
   <php>
    <min>5.5.9</min>
   </php>
   <pearinstaller>
    <min>1.4.0</min>
   </pearinstaller>
  </required>
 </dependencies>
 <providesextension>protobuf</providesextension>
 <extsrcrelease />
 <changelog>
  <release>
   <version>
    <release>3.1.0a1</release>
    <api>3.1.0a1</api>
   </version>
   <stability>
    <release>alpha</release>
    <api>alpha</api>
   </stability>
   <date>2016-09-23</date>
   <time>16:06:07</time>
   <license uri="https://opensource.org/licenses/BSD-3-Clause">3-Clause BSD License</license>
   <notes>
First alpha release
   </notes>
  </release>
  <release>
   <version>
    <release>3.2.0a1</release>
    <api>3.2.0a1</api>
   </version>
   <stability>
    <release>alpha</release>
    <api>alpha</api>
   </stability>
   <date>2017-01-13</date>
   <time>16:06:07</time>
   <license uri="https://opensource.org/licenses/BSD-3-Clause">3-Clause BSD License</license>
   <notes>
Second alpha release.
   </notes>
  </release>
  <release>
   <version>
    <release>3.3.0</release>
    <api>3.3.0</api>
   </version>
   <stability>
    <release>stable</release>
    <api>stable</api>
   </stability>
   <date>2017-04-28</date>
   <time>16:06:07</time>
   <license uri="https://opensource.org/licenses/BSD-3-Clause">3-Clause BSD License</license>
   <notes>
GA release.
   </notes>
  </release>
  <release>
   <version>
    <release>3.3.1</release>
    <api>3.3.0</api>
   </version>
   <stability>
    <release>stable</release>
    <api>stable</api>
   </stability>
   <date>2017-05-08</date>
   <time>15:33:07</time>
   <license uri="https://opensource.org/licenses/BSD-3-Clause">3-Clause BSD License</license>
   <notes>
GA release.
   </notes>
  </release>
  <release>
   <version>
    <release>3.3.2</release>
    <api>3.3.0</api>
   </version>
   <stability>
    <release>stable</release>
    <api>stable</api>
   </stability>
   <date>2017-06-21</date>
   <time>15:33:07</time>
   <license uri="https://opensource.org/licenses/BSD-3-Clause">3-Clause BSD License</license>
   <notes>
GA release.
   </notes>
  </release>
  <release>
   <version>
    <release>3.4.0</release>
    <api>3.4.0</api>
   </version>
   <stability>
    <release>stable</release>
    <api>stable</api>
   </stability>
   <date>2017-08-16</date>
   <time>15:33:07</time>
   <license uri="https://opensource.org/licenses/BSD-3-Clause">3-Clause BSD License</license>
   <notes>
GA release.
   </notes>
  </release>
  <release>
   <version>
    <release>3.4.1</release>
    <api>3.4.1</api>
   </version>
   <stability>
    <release>stable</release>
    <api>stable</api>
   </stability>
   <date>2017-09-14</date>
   <time>11:02:07</time>
   <license uri="https://opensource.org/licenses/BSD-3-Clause">3-Clause BSD License</license>
   <notes>
GA release.
   </notes>
  </release>
  <release>
   <version>
    <release>3.5.0.1</release>
    <api>3.5.0.1</api>
   </version>
   <stability>
    <release>stable</release>
    <api>stable</api>
   </stability>
   <date>2017-12-06</date>
   <time>11:02:07</time>
   <license uri="https://opensource.org/licenses/BSD-3-Clause">3-Clause BSD License</license>
   <notes>
GA release.
   </notes>
  </release>
 </changelog>
</package>
