<?xml version="1.0" encoding="UTF-8"?>
<package packagerversion="1.10.5" version="2.0" xmlns="http://pear.php.net/dtd/package-2.0" xmlns:tasks="http://pear.php.net/dtd/tasks-1.0" xmlns:xsi="http://www.w3.org/2001/XMLSchema-instance" xsi:schemaLocation="http://pear.php.net/dtd/tasks-1.0 http://pear.php.net/dtd/tasks-1.0.xsd http://pear.php.net/dtd/package-2.0 http://pear.php.net/dtd/package-2.0.xsd">
 <name>ibm_db2</name>
 <channel>pecl.php.net</channel>
 <summary>Extension for IBM DB2 Universal Database, IBM Cloudscape, and
        Apache Derby</summary>
 <description>This extension supports IBM DB2 Universal Database, IBM
Cloudscape, and Apache Derby databases.</description>
 <lead>
  <name>Venkatesh Babu K.S</name>
  <user>vnkbabu</user>
  <email>vsatyanarayana@rocketsoftware.com</email>
  <active>yes</active>
 </lead>
 <lead>
  <name>IBM OpenDev</name>
  <user>kfbombar</user>
  <email>opendev@us.ibm.com</email>
  <active>yes</active>
 </lead>
 <date>2019-04-01</date>
 <time>12:15:03</time>
 <version>
  <release>2.0.7</release>
  <api>2.0.7</api>
 </version>
 <stability>
  <release>stable</release>
  <api>stable</api>
 </stability>
 <license>Apache License 2.0</license>
 <notes>
Added PHP 7.3 Support.
 </notes>
 <contents>
  <dir name="/">
   <file baseinstalldir="ibm_db2" md5sum="7aef64bc73e840ba12ca092812ebeebf" name="tests/connection.inc" role="test" />
   <file baseinstalldir="ibm_db2" md5sum="2442b29ff165a419f1c78516bbb66d70" name="tests/rollbackhandler.inc" role="test" />
   <file baseinstalldir="ibm_db2" md5sum="c4be2ea562052d6e7f78ae8d101089cf" name="tests/escape.dat" role="test" />
   <file baseinstalldir="ibm_db2" md5sum="63154ff0b723fc7324098b4a3d40c81a" name="tests/pic1.jpg" role="test" />
   <file baseinstalldir="ibm_db2" md5sum="fad5e9c85a5f5dc6ca6eff51fddd5639" name="tests/resume_000130.txt" role="test" />
   <file baseinstalldir="ibm_db2" md5sum="eb89aa55ffa86b410d445341ce9a2e91" name="tests/resume_000140.txt" role="test" />
   <file baseinstalldir="ibm_db2" md5sum="8c6d765bd112d9c592e8da3c922b8266" name="tests/resume_000150.txt" role="test" />
   <file baseinstalldir="ibm_db2" md5sum="efe5d4097f49fecd2f23f7a163169ca6" name="tests/resume_000190.txt" role="test" />
   <file baseinstalldir="ibm_db2" md5sum="89ce9eda934944ff989ff1ea1d4e6238" name="tests/skipif.inc" role="test" />
   <file baseinstalldir="ibm_db2" md5sum="296e1ff0fd1841b5b963673990ac1a78" name="tests/skipif.PASE" role="test" />
   <file baseinstalldir="ibm_db2" md5sum="3af8145d5078376832709cefd0bfccc6" name="tests/skipif2.inc" role="test" />
   <file baseinstalldir="ibm_db2" md5sum="34139dfbe93591733a61cdd3a8d97b5b" name="tests/skipif3.inc" role="test" />
   <file baseinstalldir="ibm_db2" md5sum="6bc5288cd3c6203ddd401e833f04d363" name="tests/skipifNotRowcountPrefetch.inc" role="test" />
   <file baseinstalldir="ibm_db2" md5sum="e5979ed4595997a1edb9f61c54db8209" name="tests/skipifNotTrustedContext.inc" role="test" />
   <file baseinstalldir="ibm_db2" md5sum="10a7d4a0d86f777ae1ebcf9b3ec4d1ae" name="tests/spook.png" role="test" />
   <file baseinstalldir="ibm_db2" md5sum="f91bfd4826b9254a996f9cb5f704a106" name="tests/xmlservice.inc" role="test" />
   <file baseinstalldir="ibm_db2" md5sum="f018427d27f6f4f24d5483fcde58565a" name="tests/skipifNot10_5.inc" role="test" />
   <file baseinstalldir="ibm_db2" md5sum="c8a83210f018a49fb27b4350ed2df296" name="tests/skipifTBD.inc" role="test" />
   <file baseinstalldir="ibm_db2" md5sum="14f372bc035e593ea83c60ce722fed23" name="tests/test_001_ConnDb.phpt" role="test" />
   <file baseinstalldir="ibm_db2" md5sum="b477bb3ca38f63f7dedc881d5bc6ad22" name="tests/test_002_ConnDbUncatalogedConn.phpt" role="test" />
   <file baseinstalldir="ibm_db2" md5sum="7b170a1d432163acde36c3a19cae5e0a" name="tests/test_03a_ResultNonExistCol.phpt" role="test" />
   <file baseinstalldir="ibm_db2" md5sum="c42dc358ebd5720a9db2ecf40823a2eb" name="tests/test_003_NumAffectedRows.phpt" role="test" />
   <file baseinstalldir="ibm_db2" md5sum="028c155a0abf175e9330c6df54a140bd" name="tests/test_004_ConnWrongUserPwd.phpt" role="test" />
   <file baseinstalldir="ibm_db2" md5sum="41f772bc8bedd4b11659b7cc92ea70b7" name="tests/test_005_ConnBadUserBadPwd.phpt" role="test" />
   <file baseinstalldir="ibm_db2" md5sum="58e308306139e62aea285d1ddaf73583" name="tests/test_006_ConnPassingOpts.phpt" role="test" />
   <file baseinstalldir="ibm_db2" md5sum="5555e3d541018805f20fa0eeb71f47db" name="tests/test_007_pConnPassingOpts.phpt" role="test" />
   <file baseinstalldir="ibm_db2" md5sum="40abce525790920f280024ef371a21e3" name="tests/test_010_UpdateRowCount.phpt" role="test" />
   <file baseinstalldir="ibm_db2" md5sum="61361d578e8a6c54aafaa8317c59d88e" name="tests/test_011_DeleteRowCount.phpt" role="test" />
   <file baseinstalldir="ibm_db2" md5sum="55dd7aa913d5b1c48daabe4d4a711191" name="tests/test_012_ScrollableCursorSelectRowCount01.phpt" role="test" />
   <file baseinstalldir="ibm_db2" md5sum="98e86d4fbbe7b2e0159c37f3914e8506" name="tests/test_013_ScrollableCursorSelectRowCount02.phpt" role="test" />
   <file baseinstalldir="ibm_db2" md5sum="520b49e3c3dbef736d99c330bed94517" name="tests/test_014_ScrollableCursorRetrieveNegativeRow.phpt" role="test" />
   <file baseinstalldir="ibm_db2" md5sum="723c6710460aeac915c6f99736d1f222" name="tests/test_015_InsertDeleteRowCount_01.phpt" role="test" />
   <file baseinstalldir="ibm_db2" md5sum="8c98c43487ccbe19fc02d8faa2019585" name="tests/test_016_InsertDeleteRowCount_02.phpt" role="test" />
   <file baseinstalldir="ibm_db2" md5sum="9ea1f087fac020f0922a9b89f83e7642" name="tests/test_017_selectRowcountPrefetchSTMTOpt.phpt" role="test" />
   <file baseinstalldir="ibm_db2" md5sum="31a96f6a50b8ae00ca3573c21b4bbffb" name="tests/test_018_selectRowcountPrefetchSetOpt.phpt" role="test" />
   <file baseinstalldir="ibm_db2" md5sum="776e437604d8c80a640f74e7230c0fcd" name="tests/test_019_selectRowcountPrefetchPrepOpt.phpt" role="test" />
   <file baseinstalldir="ibm_db2" md5sum="180a3b22f608518d52725a0545fb6698" name="tests/test_020_RollbackDelete.phpt" role="test" />
   <file baseinstalldir="ibm_db2" md5sum="01a82a2b2f762e0c0e1914e0ed580ef2" name="tests/test_021_CommitDelete.phpt" role="test" />
   <file baseinstalldir="ibm_db2" md5sum="3fc0b65876d4ad3422f85af07ed0a8ac" name="tests/test_022_RollbackInsert.phpt" role="test" />
   <file baseinstalldir="ibm_db2" md5sum="23781b174dad063ef1e04191bf8c030f" name="tests/test_023_ColumnPrivileges.phpt" role="test" />
   <file baseinstalldir="ibm_db2" md5sum="c289440439bbd21ce906deab01fcdd6d" name="tests/test_024_ForeignKeys.phpt" role="test" />
   <file baseinstalldir="ibm_db2" md5sum="a2230905e1cb89f4f08cd070e2ff80d4" name="tests/test_025_PrimaryKeys.phpt" role="test" />
   <file baseinstalldir="ibm_db2" md5sum="5b83e8976b111e83e679b383d131ced8" name="tests/test_026_BindParam.phpt" role="test" />
   <file baseinstalldir="ibm_db2" md5sum="34e43604aa6bf5d2620986cf25518909" name="tests/test_030_Result.phpt" role="test" />
   <file baseinstalldir="ibm_db2" md5sum="76209de5b01a21c914b167ef0464e990" name="tests/test_031_ResultIndexPosition.phpt" role="test" />
   <file baseinstalldir="ibm_db2" md5sum="aba17b1366f389726535b3c24dee0276" name="tests/test_032_ResultIndexName.phpt" role="test" />
   <file baseinstalldir="ibm_db2" md5sum="274fb6da1d78cb9deac9f1c5df9f4124" name="tests/test_033_ResultOutSequenceColumn.phpt" role="test" />
   <file baseinstalldir="ibm_db2" md5sum="574506b62dd9e9a5ce71823d05d02f4b" name="tests/test_034_FetchRow.phpt" role="test" />
   <file baseinstalldir="ibm_db2" md5sum="36ec7363edf7288f7d36cbdc41341193" name="tests/test_035_FetchRowMany_01.phpt" role="test" />
   <file baseinstalldir="ibm_db2" md5sum="fef76e9fa4886db7c13af0888d599970" name="tests/test_036_FetchRowMany_02.phpt" role="test" />
   <file baseinstalldir="ibm_db2" md5sum="017cd4ba1330db0cdd58e664d376cedc" name="tests/test_037_FetchRowIndexPos.phpt" role="test" />
   <file baseinstalldir="ibm_db2" md5sum="12e8751643f301e8587d51761fe3cf04" name="tests/test_038_FetchRowIndexPosNested_01.phpt" role="test" />
   <file baseinstalldir="ibm_db2" md5sum="1c2bceaa1cfec011c329580f0326df69" name="tests/test_039_FetchRowIndexPosNested_02.phpt" role="test" />
   <file baseinstalldir="ibm_db2" md5sum="5433152fbf383ff9bb1abf0b433e8194" name="tests/test_040_FetchArray.phpt" role="test" />
   <file baseinstalldir="ibm_db2" md5sum="8c6f7cd0b6bcda3966ab8dedd768942a" name="tests/test_041_FetchArrayMany_01.phpt" role="test" />
   <file baseinstalldir="ibm_db2" md5sum="4ff74a29b032492d3d6bf13fafd7b82e" name="tests/test_042_FetchArrayMany_02.phpt" role="test" />
   <file baseinstalldir="ibm_db2" md5sum="9c5b7602d2236dd201ef2095003ce1c1" name="tests/test_043_FetchArrayMany_03.phpt" role="test" />
   <file baseinstalldir="ibm_db2" md5sum="72c8d06643b8712c3d2f8a2e82b9714b" name="tests/test_044_FetchArrayMany_04.phpt" role="test" />
   <file baseinstalldir="ibm_db2" md5sum="ff417fde9eb11b6b4d224eb7ef6d80d9" name="tests/test_045_FetchArrayBinaryData.phpt" role="test" />
   <file baseinstalldir="ibm_db2" md5sum="a2cc11aae88f44f09ad84c7d9fd3b42d" name="tests/test_046_FetchArrayMany_05.phpt" role="test" />
   <file baseinstalldir="ibm_db2" md5sum="b1d2263b56c42ce3b2bd68b9b347904a" name="tests/test_047_FetchArrayMany_06.phpt" role="test" />
   <file baseinstalldir="ibm_db2" md5sum="421f83d2378f229f0718e6d1845afd76" name="tests/test_048_FetchArrayBinaryData.phpt" role="test" />
   <file baseinstalldir="ibm_db2" md5sum="d2ca3522b0eaefd4b7943475709a31e6" name="tests/test_049_BindParamInsertStmtNULL.phpt" role="test" />
   <file baseinstalldir="ibm_db2" md5sum="3c033de5aa001e7b8731d5cca43d489b" name="tests/test_050_GetAutocommit.phpt" role="test" />
   <file baseinstalldir="ibm_db2" md5sum="8ea3d4652ce8d3a9eedabb4de32e73a6" name="tests/test_051_SetAutocommit.phpt" role="test" />
   <file baseinstalldir="ibm_db2" md5sum="4a22dd0a9396232e96b9aa4b7ba4f92a" name="tests/test_052_SetAutocommit_01.phpt" role="test" />
   <file baseinstalldir="ibm_db2" md5sum="5651f85f4c52dced9d21533f5682a602" name="tests/test_053_SetAutocommit_02.phpt" role="test" />
   <file baseinstalldir="ibm_db2" md5sum="bfdb5e8a23cefc5bf544a8833f0c0f94" name="tests/test_060_Tables_01.phpt" role="test" />
   <file baseinstalldir="ibm_db2" md5sum="f8c41676dd77d1732001f37123c91da4" name="tests/test_061_Tables_02.phpt" role="test" />
   <file baseinstalldir="ibm_db2" md5sum="b8bd5bfde1a0f4f0b5987d2b53c13aaf" name="tests/test_062_Tables_03.phpt" role="test" />
   <file baseinstalldir="ibm_db2" md5sum="4090d557f1ac790d6548d92643a787e3" name="tests/test_063_Tables_04.phpt" role="test" />
   <file baseinstalldir="ibm_db2" md5sum="9a398b0a3bc908e47f1180971ef2da7f" name="tests/test_064_Tables_05.phpt" role="test" />
   <file baseinstalldir="ibm_db2" md5sum="96defb32186d3d450b11ff94ffec98fb" name="tests/test_065_FilterTableName.phpt" role="test" />
   <file baseinstalldir="ibm_db2" md5sum="652eeb27bf70aed605049a202aa054fd" name="tests/test_066_TableObjects.phpt" role="test" />
   <file baseinstalldir="ibm_db2" md5sum="d09e9a3bf86385e9741677dfd2f316b0" name="tests/test_070_Close.phpt" role="test" />
   <file baseinstalldir="ibm_db2" md5sum="e33421d27c2c78aeb2d3f752988cade6" name="tests/test_071_CloseSuccess.phpt" role="test" />
   <file baseinstalldir="ibm_db2" md5sum="4e91e86f294c9db0e043445a43da39ed" name="tests/test_080_ConnWrongDbAlias.phpt" role="test" />
   <file baseinstalldir="ibm_db2" md5sum="89e14a97f05514bedce23d37889f87c4" name="tests/test_081_ConnWrongUser.phpt" role="test" />
   <file baseinstalldir="ibm_db2" md5sum="8c1bd708854caa30523309ddbb77816a" name="tests/test_082_ConnWrongPwd.phpt" role="test" />
   <file baseinstalldir="ibm_db2" md5sum="66b25a4a065d15559806eb8ccbd5afad" name="tests/test_090_ConnmsgWrongDbAlias.phpt" role="test" />
   <file baseinstalldir="ibm_db2" md5sum="926221ea0b1e75fe48940c6a92ceb6dd" name="tests/test_091_ConnmsgWrongUser.phpt" role="test" />
   <file baseinstalldir="ibm_db2" md5sum="956bffa5a38bd82ecddc2e50462bacc6" name="tests/test_092_ConnmsgWrongPwd.phpt" role="test" />
   <file baseinstalldir="ibm_db2" md5sum="129b3ac7c22be8fc2d75b5e05bcb5e51" name="tests/test_100_SelectDeleteInsertFieldCount.phpt" role="test" />
   <file baseinstalldir="ibm_db2" md5sum="2cdfa283dcbb6c2e9d2a94e50f0c1703" name="tests/test_101_InsertDeleteFieldCount.phpt" role="test" />
   <file baseinstalldir="ibm_db2" md5sum="7d0cc3debca5f98fbd60e30b78a277b6" name="tests/test_102_NumFieldsSelect_01.phpt" role="test" />
   <file baseinstalldir="ibm_db2" md5sum="9fbad2f3159420e3a792a8f9b1a9d5a9" name="tests/test_103_NumFieldsSelect_02.phpt" role="test" />
   <file baseinstalldir="ibm_db2" md5sum="141196cb5c3224b7abf5e91fd5fe0b93" name="tests/test_110_FieldNum.phpt" role="test" />
   <file baseinstalldir="ibm_db2" md5sum="de9e7c9ab4ede45f42360eafcd8e1435" name="tests/test_111_FieldNumAddCol.phpt" role="test" />
   <file baseinstalldir="ibm_db2" md5sum="1b7e7df7b70f9286453f25a1a3fee5ad" name="tests/test_112_FieldNumDiffCaseColNames.phpt" role="test" />
   <file baseinstalldir="ibm_db2" md5sum="2db7f932a2d449a7339ce791b173a218" name="tests/test_120_FieldName.phpt" role="test" />
   <file baseinstalldir="ibm_db2" md5sum="fc036c987d9c43bc955d0db491044fb3" name="tests/test_121_FieldNameAddCol.phpt" role="test" />
   <file baseinstalldir="ibm_db2" md5sum="098b663af5694ccf8e25d24756e3442d" name="tests/test_122_FieldNameDiffCaseColNames.phpt" role="test" />
   <file baseinstalldir="ibm_db2" md5sum="aa4d9055a7857457c875214dc6e20133" name="tests/test_123_FieldNamePos_01.phpt" role="test" />
   <file baseinstalldir="ibm_db2" md5sum="5e80094cd3d38c5d463afd9b4b971fcf" name="tests/test_124_FieldNamePos_02.phpt" role="test" />
   <file baseinstalldir="ibm_db2" md5sum="b0ca5e9fa4b3a9cb1b0d33b2096992bc" name="tests/test_125_FieldNamePos_03.phpt" role="test" />
   <file baseinstalldir="ibm_db2" md5sum="762277007a873e14c5f0fa97ea4c75cc" name="tests/test_130_PrepExecuteSelectStmt.phpt" role="test" />
   <file baseinstalldir="ibm_db2" md5sum="3292807b17505feec42117d575f0bcc1" name="tests/test_131a_PrepExecuteDataTypeConversionsErrs.phpt" role="test" />
   <file baseinstalldir="ibm_db2" md5sum="6578b5cd78b330a86920ef3bd15b4019" name="tests/test_131_PrepareExecuteSelectStatementParams.phpt" role="test" />
   <file baseinstalldir="ibm_db2" md5sum="936edfe7c2cc987726523c3192630b01" name="tests/test_132_ExecuteStatementArrayMultipleParams.phpt" role="test" />
   <file baseinstalldir="ibm_db2" md5sum="2bfa2b244758a0a7e15f7dbc6a90e188" name="tests/test_133_ExecuteLongInputParams.phpt" role="test" />
   <file baseinstalldir="ibm_db2" md5sum="8c03c96f9e4055ef307acd5d30f4e882" name="tests/test_140_BindParamSelectStmt.phpt" role="test" />
   <file baseinstalldir="ibm_db2" md5sum="05f49c189754071156830155b227a1c3" name="tests/test_141_BindParamSelectStmtMultipleParams_01.phpt" role="test" />
   <file baseinstalldir="ibm_db2" md5sum="de2b7e87104c706c5b03f8e213c4581b" name="tests/test_142_BindParamSelectStmtMultipleParams_02.phpt" role="test" />
   <file baseinstalldir="ibm_db2" md5sum="197715d5e916df354a35487fd3d5aec9" name="tests/test_143_BindParamInsertStmtNULLParam.phpt" role="test" />
   <file baseinstalldir="ibm_db2" md5sum="cc637b8531aad2d03ca10df289d24b88" name="tests/test_144_BindParamInsertStmtPARAM_FILE.phpt" role="test" />
   <file baseinstalldir="ibm_db2" md5sum="b8c437ba84bb83284a3ecd2842ce6da2" name="tests/test_145_BindRetrieveNULLEmptyString.phpt" role="test" />
   <file baseinstalldir="ibm_db2" md5sum="1c3662f0bcbcdee2cfb3df5e09c73453" name="tests/test_146_CallSPINAndOUTParams.phpt" role="test" />
   <file baseinstalldir="ibm_db2" md5sum="669abb8a94c79d0310c6e2e0aafb825a" name="tests/test_147_CallSPINAndOUTParamsMultipleTimes.phpt" role="test" />
   <file baseinstalldir="ibm_db2" md5sum="6ea7bb433eee6ca522baa31f32dbd508" name="tests/test_148_CallSPDiffBindPattern_01.phpt" role="test" />
   <file baseinstalldir="ibm_db2" md5sum="81e05373b8b950fdd3007b26c74bf2f9" name="tests/test_149_CallSPDiffBindPattern_02.phpt" role="test" />
   <file baseinstalldir="ibm_db2" md5sum="6dd8c688f9099062d2bf43a4d3398657" name="tests/test_150_FetchAssocSelect_01.phpt" role="test" />
   <file baseinstalldir="ibm_db2" md5sum="8780a13f12e0b22407526ff88672b73d" name="tests/test_151_FetchAssocSelect_02.phpt" role="test" />
   <file baseinstalldir="ibm_db2" md5sum="273fb66054cdb2f9126d0b41cd4a1e03" name="tests/test_152_FetchAssocSelect_03.phpt" role="test" />
   <file baseinstalldir="ibm_db2" md5sum="8a9cbdc1a9e2961b974d92feda485ca0" name="tests/test_153_FetchAssocSelect_04.phpt" role="test" />
   <file baseinstalldir="ibm_db2" md5sum="ab5974aa63c27c068dc117188047e030" name="tests/test_154_AllFetches.phpt" role="test" />
   <file baseinstalldir="ibm_db2" md5sum="5d58f0572c031991fe81d0173e35cfeb" name="tests/test_155_FetchAssocSelect_06.phpt" role="test" />
   <file baseinstalldir="ibm_db2" md5sum="fc1bbf5dcaa61bf937ac11815c1859f5" name="tests/test_156_FetchAssocNestedSelects_01.phpt" role="test" />
   <file baseinstalldir="ibm_db2" md5sum="fa58b48daac1621067928b4756adbbfb" name="tests/test_157a_FetchAssocWithoutScrollableCursorErr.phpt" role="test" />
   <file baseinstalldir="ibm_db2" md5sum="0c81ab0237a2a697fb5c06e587c86b48" name="tests/test_157b_FetchAssocScrollableCursor_01.phpt" role="test" />
   <file baseinstalldir="ibm_db2" md5sum="99c91b6dc6cbc2f0e0dee96305fdcf5a" name="tests/test_157_FetchAssocScrollableCursor_02.phpt" role="test" />
   <file baseinstalldir="ibm_db2" md5sum="adb50630dd703e9e1f713d18b6162c7d" name="tests/test_158_FetchAssocNestedSelects_02.phpt" role="test" />
   <file baseinstalldir="ibm_db2" md5sum="81a41808c72092f42db6381c5cee2b6d" name="tests/test_159a_FetchAssocSeveralRows_02.phpt" role="test" />
   <file baseinstalldir="ibm_db2" md5sum="7013087a965a93042a2f2ac3cc19e250" name="tests/test_159_FetchAssocSeveralRows_01.phpt" role="test" />
   <file baseinstalldir="ibm_db2" md5sum="6b4309ba00c50cd5f08aa7d7da613d08" name="tests/test_160_FetchBoth.phpt" role="test" />
   <file baseinstalldir="ibm_db2" md5sum="fa01c2239376772e320aae85dcdc7c39" name="tests/test_161_FetchBothNestedSelects_01.phpt" role="test" />
   <file baseinstalldir="ibm_db2" md5sum="45152dcffee86c3f750c5874fe445b6b" name="tests/test_162_FetchBothNestedSelects_02.phpt" role="test" />
   <file baseinstalldir="ibm_db2" md5sum="9d5650b5d4e2a004be259e32108a6c3f" name="tests/test_163_FetchBothBinary.phpt" role="test" />
   <file baseinstalldir="ibm_db2" md5sum="900ee3168d5c9905a5ff8515a8b29152" name="tests/test_180_StmtErrMsg.phpt" role="test" />
   <file baseinstalldir="ibm_db2" md5sum="6498f6f62554167544d59fa69d5a7109" name="tests/test_190_ColumnsTable_01.phpt" role="test" />
   <file baseinstalldir="ibm_db2" md5sum="d29f009c2f59b25d37813f85da521f63" name="tests/test_191_ColumnsTable_02.phpt" role="test" />
   <file baseinstalldir="ibm_db2" md5sum="a5a003dbfe2bccaae8e5ab1d6735818a" name="tests/test_192_ColumnsTable_03.phpt" role="test" />
   <file baseinstalldir="ibm_db2" md5sum="32c6459902f8e94e4af42b160a575d8b" name="tests/test_193_RetrieveCLOBColFwdOnly.phpt" role="test" />
   <file baseinstalldir="ibm_db2" md5sum="20c84b5a7dd74b8520e3007810a20508" name="tests/test_194_RetrieveCLOBColScrollable.phpt" role="test" />
   <file baseinstalldir="ibm_db2" md5sum="3b9c3b86f3d023035ca6c3872e23d3d3" name="tests/test_195_InsertRetrieveXMLData_01.phpt" role="test" />
   <file baseinstalldir="ibm_db2" md5sum="e12ccd0b51c9e33d59704910a3344451" name="tests/test_196_InsertRetrieveXMLData_02.phpt" role="test" />
   <file baseinstalldir="ibm_db2" md5sum="36f77c55e5c211fa3e62cdd81b97e7ce" name="tests/test_197_StatisticsIndexes.phpt" role="test" />
   <file baseinstalldir="ibm_db2" md5sum="c306cf839031e51be6e31aeadf64108a" name="tests/test_198_LobReadWriteFromMemory.phpt" role="test" />
   <file baseinstalldir="ibm_db2" md5sum="6845c6d2a7450e389fdf00ad00d162d9" name="tests/test_200_MultipleRsltsetsUniformColDefs.phpt" role="test" />
   <file baseinstalldir="ibm_db2" md5sum="c4d7ffae100d15276891fe7687bec691" name="tests/test_201_MultipleRsltsetsDiffColDefs.phpt" role="test" />
   <file baseinstalldir="ibm_db2" md5sum="5e5599af53aa3c4cbb621cb02ff2a732" name="tests/test_210_FieldDisplaySize_01.phpt" role="test" />
   <file baseinstalldir="ibm_db2" md5sum="a998dc821a131bb61fda431305d004d7" name="tests/test_211_FieldDisplaySize_02.phpt" role="test" />
   <file baseinstalldir="ibm_db2" md5sum="735873d3dbcdc288f8a8b071d5dfeab9" name="tests/test_212_FieldDisplaySize_03.phpt" role="test" />
   <file baseinstalldir="ibm_db2" md5sum="1db6d9d1e00eb42e44b7a643f9265a39" name="tests/test_213_FieldDisplaySize_04.phpt" role="test" />
   <file baseinstalldir="ibm_db2" md5sum="d7a835ad250e2d502ef05d3e249bb10f" name="tests/test_220_PersistentConn.phpt" role="test" />
   <file baseinstalldir="ibm_db2" md5sum="f70fb9d5e58ce0125667de0fd424adc4" name="tests/test_221_100PersistentConns.phpt" role="test" />
   <file baseinstalldir="ibm_db2" md5sum="def0bf7e339735407d394b8e166f8add" name="tests/test_230_FieldTypePos.phpt" role="test" />
   <file baseinstalldir="ibm_db2" md5sum="7c79324df68613b654472111a3efaf8f" name="tests/test_231_FieldTypeName.phpt" role="test" />
   <file baseinstalldir="ibm_db2" md5sum="a6629d7c9e69a7384fe2cb9e61849d33" name="tests/test_232_FieldTypePosName.phpt" role="test" />
   <file baseinstalldir="ibm_db2" md5sum="05701ce116f4c142f65d1fc6d76d813b" name="tests/test_240_FieldWidthPosName_01.phpt" role="test" />
   <file baseinstalldir="ibm_db2" md5sum="139676ca49d906576dde1e8caf882f40" name="tests/test_241_FieldWidthPosName_02.phpt" role="test" />
   <file baseinstalldir="ibm_db2" md5sum="36b5c5d47cdbc2ce6ca1d38de5e7dd7a" name="tests/test_250_FreeResult_01.phpt" role="test" />
   <file baseinstalldir="ibm_db2" md5sum="2aca697eac1cf7197070c6351e14eb85" name="tests/test_251_FreeResult_02.phpt" role="test" />
   <file baseinstalldir="ibm_db2" md5sum="bbd0ac5c38d8f6e070dbd145a8f769ac" name="tests/test_252_FreeResult_03.phpt" role="test" />
   <file baseinstalldir="ibm_db2" md5sum="10bb3b50067670cd2eec3249c42f37c1" name="tests/test_260_FetchObject.phpt" role="test" />
   <file baseinstalldir="ibm_db2" md5sum="da7cdcc5ef561b02cfb75dc865f18fde" name="tests/test_261_FetchObjectAccess.phpt" role="test" />
   <file baseinstalldir="ibm_db2" md5sum="1a48ffecc4cd7226cf0ba380e3c85076" name="tests/test_263_XML_OUTParamsInSPs.phpt" role="test" />
   <file baseinstalldir="ibm_db2" md5sum="61a9d5db380c30d55f2b5aa50273d6e0" name="tests/test_264_InsertRetrieveBIGINTTypeColumn.phpt" role="test" />
   <file baseinstalldir="ibm_db2" md5sum="e29460d0b0e75d793cb4291f1847a48b" name="tests/test_300_ServerInfo.phpt" role="test" />
   <file baseinstalldir="ibm_db2" md5sum="def4aaca242d8634a9c3ae11f03e0508" name="tests/test_310_ClientInfo.phpt" role="test" />
   <file baseinstalldir="ibm_db2" md5sum="92aa6c75454a2341f0d583c4a6a53cb1" name="tests/test_320_EscapeString.phpt" role="test" />
   <file baseinstalldir="ibm_db2" md5sum="a1a4b2ffca1dd7bdeca6adbc0eda010b" name="tests/test_321_ResultFetchArraysLobsXMLTypes.phpt" role="test" />
   <file baseinstalldir="ibm_db2" md5sum="4277d7b93363ccd09856faab2cea2b09" name="tests/test_1551_FetchAssocBinary.phpt" role="test" />
   <file baseinstalldir="ibm_db2" md5sum="548be41e3f6c7daffac82209983de7e2" name="tests/test_6528_ScopingProblemBindParam.phpt" role="test" />
   <file baseinstalldir="ibm_db2" md5sum="6166d05ed3bb0c4c57b3eecb6cacbf2a" name="tests/test_6561_ReturnNULLValues.phpt" role="test" />
   <file baseinstalldir="ibm_db2" md5sum="e8e6237b4ac957504d2fae6047ce5a8a" name="tests/test_6572_SQLStringsContNULLChar.phpt" role="test" />
   <file baseinstalldir="ibm_db2" md5sum="329de70b0401ccbed2fbe59ace553043" name="tests/test_6755_ExtraNULLChar_ResultCLOBCol.phpt" role="test" />
   <file baseinstalldir="ibm_db2" md5sum="6ab45d18b8f25e09ef396e97d0e0501f" name="tests/test_9173_ProcedurePersistentConn.phpt" role="test" />
   <file baseinstalldir="ibm_db2" md5sum="f3adb38352ddde0c41e16fadfade5fa5" name="tests/test_9194_FetchBothCLOBColumns.phpt" role="test" />
   <file baseinstalldir="ibm_db2" md5sum="98f74d77390e4e2bdb9e1a729f49890c" name="tests/test_10353_MemLeak.phpt" role="test" />
   <file baseinstalldir="ibm_db2" md5sum="14842007fe6c1afd1ec05325a7baeb23" name="tests/test_10931_LcaseTableName.phpt" role="test" />
   <file baseinstalldir="ibm_db2" md5sum="8ec9b5e90eb3360a1dc1895031e1b8cb" name="tests/test_clob_special_char.phpt" role="test" />
   <file baseinstalldir="ibm_db2" md5sum="602a8fd722d7bcd326b31bea79e268fd" name="tests/test_decfloat.phpt" role="test" />
   <file baseinstalldir="ibm_db2" md5sum="3ee58e26e0a080c9655f9aaee1128873" name="tests/test_graphic_data_type.phpt" role="test" />
   <file baseinstalldir="ibm_db2" md5sum="2cffce30412fb66896de262a44fba115" name="tests/test_last_insert_id.phpt" role="test" />
   <file baseinstalldir="ibm_db2" md5sum="7ecc449309b21e5801a1de3929e94201" name="tests/test_queryTimeout.phpt" role="test" />
   <file baseinstalldir="ibm_db2" md5sum="06912be31b4d6a45635928cd365e96da" name="tests/test_RealDataType.phpt" role="test" />
   <file baseinstalldir="ibm_db2" md5sum="276edcda87d2e7095688aa5832724be5" name="tests/test_timestamp.phpt" role="test" />
   <file baseinstalldir="ibm_db2" md5sum="da978ce79e76f722d86e0def32479ac5" name="tests/test_trusted_context_connect.phpt" role="test" />
   <file baseinstalldir="ibm_db2" md5sum="5bd6716c7a4c3035265fe33c74348ad0" name="tests/test_trusted_context_pconnect.phpt" role="test" />
   <file baseinstalldir="ibm_db2" md5sum="38201bc6985b14991fec23e8b467725a" name="tests/test_000_PrepareDb.phpt" role="test" />
   <file baseinstalldir="ibm_db2" md5sum="f0c93781d7d798ff30a3e1552943d101" name="tests/trusted_connection.inc" role="test" />
   <file baseinstalldir="ibm_db2" md5sum="3ee58e26e0a080c9655f9aaee1128873" name="tests/test_graphic_data_type.phpt" role="test" />
   <file baseinstalldir="ibm_db2" md5sum="c60e3821001ad8952aac4bd6c42051cb" name="tests/test_check_rollback.phpt" role="test" />
   <file baseinstalldir="ibm_db2" md5sum="2d5850fd6bd2b6ce856ad653d6ba6296" name="tests/test_connect_deallocator.phpt" role="test" />
   <file baseinstalldir="ibm_db2" md5sum="dc087e0eb8332090373bd8c3b1bcbb5d" name="tests/test_execute_many.phpt" role="test" />
   <file baseinstalldir="ibm_db2" md5sum="d4085f36a97a4b69e6cbdeb1c66589e9" name="tests/test_bigint.phpt" role="test" />
   <file baseinstalldir="ibm_db2" md5sum="b9aaa8217369181e0208f85b1bfbfc0a" name="tests/test_V6_002_ConnDbUncatalogedConn.phpt" role="test" />
   <file baseinstalldir="ibm_db2" md5sum="0e00cd37fe447e21acc20b29e84b5763" name="tests/test_V6_023_ColumnPrivileges.phpt" role="test" />
   <file baseinstalldir="ibm_db2" md5sum="336bbe8994f70113fd2f3adf71e50af2" name="tests/test_V6_039_FetchRowIndexPosNested_02.phpt" role="test" />
   <file baseinstalldir="ibm_db2" md5sum="071a707842a6c8ed771481d7084e90ab" name="tests/test_V6_041_FetchArrayMany_01.phpt" role="test" />
   <file baseinstalldir="ibm_db2" md5sum="0e00cd37fe447e21acc20b29e84b5763" name="tests/test_V6_053_SetAutocommit_02.phpt" role="test" />
   <file baseinstalldir="ibm_db2" md5sum="112130c0e93a52d5e6b7e51e5c5746a6" name="tests/test_V6_060_Tables_01.phpt" role="test" />
   <file baseinstalldir="ibm_db2" md5sum="a54a30962983513f8ad2e55883af91dd" name="tests/test_V6_061_Tables_02.phpt" role="test" />
   <file baseinstalldir="ibm_db2" md5sum="54d68f2bb1387fb625289503b6eb9ead" name="tests/test_V6_062_Tables_03.phpt" role="test" />
   <file baseinstalldir="ibm_db2" md5sum="c97509e517d23015557da16f295971c8" name="tests/test_V6_064_Tables_05.phpt" role="test" />
   <file baseinstalldir="ibm_db2" md5sum="39a5c82aecb02a794ecf2efe30e9b2f6" name="tests/test_V6_065_FilterTableName.phpt" role="test" />
   <file baseinstalldir="ibm_db2" md5sum="d17fa6d7b4f2a9cc191b561d0a6bf393" name="tests/test_V6_066_TableObjects.phpt" role="test" />
   <file baseinstalldir="ibm_db2" md5sum="7f1777f3b02f97e415c7f88a0d1d0519" name="tests/test_V6_080_ConnWrongDbAlias.phpt" role="test" />
   <file baseinstalldir="ibm_db2" md5sum="4eaba0a1dfa5bdf654c8af91fc769832" name="tests/test_V6_090_ConnmsgWrongDbAlias.phpt" role="test" />
   <file baseinstalldir="ibm_db2" md5sum="0e00cd37fe447e21acc20b29e84b5763" name="tests/test_V6_091_ConnmsgWrongUser.phpt" role="test" />
   <file baseinstalldir="ibm_db2" md5sum="0e00cd37fe447e21acc20b29e84b5763" name="tests/test_V6_092_ConnmsgWrongPwd.phpt" role="test" />
   <file baseinstalldir="ibm_db2" md5sum="0e00cd37fe447e21acc20b29e84b5763" name="tests/test_V6_102_NumFieldsSelect_01.phpt" role="test" />
   <file baseinstalldir="ibm_db2" md5sum="0e00cd37fe447e21acc20b29e84b5763" name="tests/test_V6_10353.phpt" role="test" />
   <file baseinstalldir="ibm_db2" md5sum="0e00cd37fe447e21acc20b29e84b5763" name="tests/test_V6_10353_MemLeak.phpt" role="test" />
   <file baseinstalldir="ibm_db2" md5sum="a5a6008cdacd4b6a2d422b794a850185" name="tests/test_V6_10931_LcaseTableName.phpt" role="test" />
   <file baseinstalldir="ibm_db2" md5sum="447b15cc17ff4182836284842961af64" name="tests/test_V6_131a_PrepExecuteDataTypeConversionsErrs.phpt" role="test" />
   <file baseinstalldir="ibm_db2" md5sum="7b092c0df065e38b5fdcf7ed5b3a9542" name="tests/test_V6_133_ExecuteLongInputParams.phpt" role="test" />
   <file baseinstalldir="ibm_db2" md5sum="ebfd7e57c35fabb8cd4a343c8d6f9c2e" name="tests/test_V6_148_CallSPDiffBindPattern_01.phpt" role="test" />
   <file baseinstalldir="ibm_db2" md5sum="81e05373b8b950fdd3007b26c74bf2f9" name="tests/test_V6_149_CallSPDiffBindPattern_02.phpt" role="test" />
   <file baseinstalldir="ibm_db2" md5sum="894661e1987b850a97c37c2640aee4ab" name="tests/test_V6_160_FetchBoth.phpt" role="test" />
   <file baseinstalldir="ibm_db2" md5sum="87bd99e5a078c6bafbe49c3dc5f9bea6" name="tests/test_V6_161_FetchBothNestedSelects_01.phpt" role="test" />
   <file baseinstalldir="ibm_db2" md5sum="dfb0b464ed91df45d3ec1983d824d5fe" name="tests/test_V6_162_FetchBothNestedSelects_02.phpt" role="test" />
   <file baseinstalldir="ibm_db2" md5sum="425058b4c65319194f6000518d3e2798" name="tests/test_V6_180_StmtErrMsg.phpt" role="test" />
   <file baseinstalldir="ibm_db2" md5sum="48c4e39fb9c97a99ff9c69a5f6fc688b" name="tests/test_V6_191_ColumnsTable_02.phpt" role="test" />
   <file baseinstalldir="ibm_db2" md5sum="4865beb3b8ba6ff422830f54447a741a" name="tests/test_V6_192_ColumnsTable_03.phpt" role="test" />
   <file baseinstalldir="ibm_db2" md5sum="2ace12f2b889c0d26a47cfc65180b4b3" name="tests/test_V6_194_RetrieveCLOBColScrollable.phpt" role="test" />
   <file baseinstalldir="ibm_db2" md5sum="0e00cd37fe447e21acc20b29e84b5763" name="tests/test_V6_195_InsertRetrieveXMLData_01.phpt" role="test" />
   <file baseinstalldir="ibm_db2" md5sum="0e00cd37fe447e21acc20b29e84b5763" name="tests/test_V6_196_InsertRetrieveXMLData_02.phpt" role="test" />
   <file baseinstalldir="ibm_db2" md5sum="46e672a2f13c012352441fd0658e903b" name="tests/test_V6_197_StatisticsIndexes.phpt" role="test" />
   <file baseinstalldir="ibm_db2" md5sum="535b9197954209736e7a2766688bc334" name="tests/test_V6_197_StatisticsIndexes_with_lib_1028_issue.phpt" role="test" />
   <file baseinstalldir="ibm_db2" md5sum="0e00cd37fe447e21acc20b29e84b5763" name="tests/test_V6_198_LobReadWriteFromMemory.phpt" role="test" />
   <file baseinstalldir="ibm_db2" md5sum="bd6b28e92fd6814bc981741a72511d48" name="tests/test_V6_201_MultipleRsltsetsDiffColDefs.phpt" role="test" />
   <file baseinstalldir="ibm_db2" md5sum="e95b378abb4291d054bebf589fdaa9ec" name="tests/test_V6_240_FieldWidthPosName_01.phpt" role="test" />
   <file baseinstalldir="ibm_db2" md5sum="090f5d5cfe01d3bfcaabd08d7a30c1eb" name="tests/test_V6_241_FieldWidthPosName_02.phpt" role="test" />
   <file baseinstalldir="ibm_db2" md5sum="b2f84d01d06fef3db79d26ffac586c34" name="tests/test_V6_260_FetchObject.phpt" role="test" />
   <file baseinstalldir="ibm_db2" md5sum="0e00cd37fe447e21acc20b29e84b5763" name="tests/test_V6_263_XML_OUTParamsInSPs.phpt" role="test" />
   <file baseinstalldir="ibm_db2" md5sum="2d207981eecc37f2d91d81fde7b0db1d" name="tests/test_V6_300_ServerInfo.phpt" role="test" />
   <file baseinstalldir="ibm_db2" md5sum="8351852d833f6fc3fd13c776bf61c5ae" name="tests/test_V6_310_ClientInfo.phpt" role="test" />
   <file baseinstalldir="ibm_db2" md5sum="ad7416a8d2f2603bb38b1ad20b06fe13" name="tests/test_V6_320_EscapeString.phpt" role="test" />
   <file baseinstalldir="ibm_db2" md5sum="0e00cd37fe447e21acc20b29e84b5763" name="tests/test_V6_321_ResultFetchArraysLobsXMLTypes.phpt" role="test" />
   <file baseinstalldir="ibm_db2" md5sum="e85cf5476529c5dcb1a35692f8e277c4" name="tests/test_V6_6792_FieldTypeRetStrDatetimeTimestamp.phpt" role="test" />
   <file baseinstalldir="ibm_db2" md5sum="6ab45d18b8f25e09ef396e97d0e0501f" name="tests/test_V6_9173_ProcedurePersistentConn.phpt" role="test" />
   <file baseinstalldir="ibm_db2" md5sum="b41f29fb3855420559fd6948b5ed1eb0" name="tests/test_V6_bigint.phpt" role="test" />
   <file baseinstalldir="ibm_db2" md5sum="0e00cd37fe447e21acc20b29e84b5763" name="tests/test_V6_clob_special_char.phpt" role="test" />
   <file baseinstalldir="ibm_db2" md5sum="c3737ace3bbbe667981543e5daa9e1ce" name="tests/test_V6_connect_deallocator.phpt" role="test" />
   <file baseinstalldir="ibm_db2" md5sum="0e00cd37fe447e21acc20b29e84b5763" name="tests/test_V6_execute_many.phpt" role="test" />
   <file baseinstalldir="ibm_db2" md5sum="0e00cd37fe447e21acc20b29e84b5763" name="tests/test_V6_graphic_data_type.phpt" role="test" />
   <file baseinstalldir="ibm_db2" md5sum="06792ddce0c097ead9ede5bfdb91a6bc" name="tests/test_V6_hebrew.phpt" role="test" />
   <file baseinstalldir="ibm_db2" md5sum="d8b6026285e6a5ae0c5026bf36a49d0c" name="tests/test_V6_ini_i5_all_pconnect.phpt" role="test" />
   <file baseinstalldir="ibm_db2" md5sum="4e7b2f5fc04ff74d02d9c30546114521" name="tests/test_V6_ini_i5_allow_commit.phpt" role="test" />
   <file baseinstalldir="ibm_db2" md5sum="d64e2fe50123b415570ce113ee901e0b" name="tests/test_V6_ini_i5_blank_userid.phpt" role="test" />
   <file baseinstalldir="ibm_db2" md5sum="ae7f34c63cf2fe12f6f57f851c51f9fa" name="tests/test_V6_ini_i5_check_pconnect.phpt" role="test" />
   <file baseinstalldir="ibm_db2" md5sum="ca1008ed9e6f8380715d6b0d681f77a9" name="tests/test_V6_ini_i5_guard_profile.phpt" role="test" />
   <file baseinstalldir="ibm_db2" md5sum="b8620e7bfd61cd7223f1ffad0f52ef61" name="tests/test_V6_ini_i5_ignore_userid.phpt" role="test" />
   <file baseinstalldir="ibm_db2" md5sum="c7f874954bbdf593a9b184fb89a059e3" name="tests/test_V6_ini_i5_max_pconnect.phpt" role="test" />
   <file baseinstalldir="ibm_db2" md5sum="35cc3c416db159bd720afb911790134e" name="tests/test_V6_ini_i5_servermode_subsystem.phpt" role="test" />
   <file baseinstalldir="ibm_db2" md5sum="b71286ab5c8d3f5f28084f4fd74fd940" name="tests/test_V6_ini_i5_sys_naming.phpt" role="test" />
   <file baseinstalldir="ibm_db2" md5sum="764ce0f0ff9fa95c1458570c68de49dc" name="tests/test_V6_last_insert_id.phpt" role="test" />
   <file baseinstalldir="ibm_db2" md5sum="4bb5b29cfaa2c9e3850360901597591d" name="tests/test_V6_timestamp.phpt" role="test" />
   <file baseinstalldir="ibm_db2" md5sum="0e00cd37fe447e21acc20b29e84b5763" name="tests/test_V6_trusted_context_connect.phpt" role="test" />
   <file baseinstalldir="ibm_db2" md5sum="0e00cd37fe447e21acc20b29e84b5763" name="tests/test_V6_trusted_context_pconnect.phpt" role="test" />
   <file baseinstalldir="ibm_db2" md5sum="d16c35ab927f78981a00447d43ba4434" name="tests/test_x001_IBMi_LUW_DB2_I5_NAMING_ON.phpt" role="test" />
   <file baseinstalldir="ibm_db2" md5sum="f8ac08d0ad42fd164d78dbaf6ebe2ddc" name="tests/test_x002_IBMi_LUW_DB2_I5_TXN_NO_COMMIT.phpt" role="test" />
   <file baseinstalldir="ibm_db2" md5sum="3e6eb0b6cc60f2c38cb3404d182b9210" name="tests/test_x010_IBMi_LUW_DB2_I5_FMT.phpt" role="test" />
   <file baseinstalldir="ibm_db2" md5sum="0f63c795eeee7fb29ce03877a0b4352a" name="config.m4" role="src" />
   <file baseinstalldir="ibm_db2" md5sum="96ef7e2a0442405549fb9000737e65fc" name="config.w32" role="src" />
   <file baseinstalldir="ibm_db2" md5sum="a7a9c499b75e84da5b876c5beabe4c7a" name="ibm_db2.c" role="src" />
   <file baseinstalldir="ibm_db2" md5sum="50c8871b7921a625bd09104fb19a677a" name="ibm_db2.dsp" role="src" />
   <file baseinstalldir="ibm_db2" md5sum="babecc59ccade7c5cd9a61fc4b71ee93" name="php_ibm_db2.h" role="src" />
   <file baseinstalldir="ibm_db2" md5sum="8fc62703cce0841cb16f9aab436fa126" name="TODO" role="doc" />
   <file baseinstalldir="ibm_db2" md5sum="2565745239557cee06d0fc4b2bbf05a5" name="LICENSE" role="doc" />
   <file baseinstalldir="ibm_db2" md5sum="919454765eaf0012832c787c8bb8305d" name="CONTRIBUTING.md" role="doc" />
   <file baseinstalldir="ibm_db2" md5sum="928d7c884b4d1430790477ae972739ef" name="README" role="doc" />
   <file baseinstalldir="ibm_db2" md5sum="dba35c658fc342be3e865239be1e3e65" name=".travis.yml" role="doc" />
  </dir>
 </contents>
 <dependencies>
  <required>
   <php>
    <min>4.0.0</min>
   </php>
   <pearinstaller>
    <min>1.4.0b1</min>
   </pearinstaller>
  </required>
 </dependencies>
 <providesextension>ibm_db2</providesextension>
 <extsrcrelease>
  <configureoption name="with-IBM_DB2" prompt="DB2 Installation Directory?" />
 </extsrcrelease>
</package>
