<?xml version="1.0" encoding="ISO-8859-1"?>
<package packagerversion="1.10.13" version="2.0" xmlns="http://pear.php.net/dtd/package-2.0" xmlns:tasks="http://pear.php.net/dtd/tasks-1.0" xmlns:xsi="http://www.w3.org/2001/XMLSchema-instance" xsi:schemaLocation="http://pear.php.net/dtd/tasks-1.0 http://pear.php.net/dtd/tasks-1.0.xsd http://pear.php.net/dtd/package-2.0 http://pear.php.net/dtd/package-2.0.xsd">
 <name>zookeeper</name>
 <channel>pecl.php.net</channel>
 <summary>PHP extension for interfacing with Apache ZooKeeper</summary>
 <description>This extension provides API for communicating with ZooKeeper service.</description>
 <lead>
  <name>Andrei Zmievski</name>
  <user>andrei</user>
  <email>andrei@php.net</email>
  <active>no</active>
 </lead>
 <lead>
  <name>Timandes White</name>
  <user>timandes</user>
  <email>timandes@php.net</email>
  <active>yes</active>
 </lead>
 <developer>
  <name>John Boehr</name>
  <user>jbboehr</user>
  <email>jbboehr@gmail.com</email>
  <active>no</active>
 </developer>
 <date>2023-02-21</date>
 <time>03:21:33</time>
 <version>
  <release>1.2.0</release>
  <api>0.7.0</api>
 </version>
 <stability>
  <release>alpha</release>
  <api>stable</api>
 </stability>
 <license uri="http://www.php.net/license">PHP</license>
 <notes>
Improvements:
- Make extension compatible with PHP 8.2 (Thanks to Federico J. Álvarez Valero and erikn69, GH PR #55, #56)
 </notes>
 <contents>
  <dir name="/">
   <file md5sum="b788abb76004a47876a0c1c1048be58e" name="examples/Zookeeper_Example.php" role="doc" />
   <file md5sum="2d0713eb39816759d0e9c6bebd8d751c" name="examples/watch.php" role="doc" />
   <file md5sum="6c47a76d2a0c1f19eadb704c39f8115e" name="README.markdown" role="doc" />
   <file md5sum="04f823bd75a30977621bc12d77ebc54d" name="CREDITS" role="doc" />
   <file md5sum="cb564efdf78cce8ea6e4b5a4f7c05d97" name="LICENSE" role="doc" />
   <file md5sum="cad4f7e998ead34459c42894e959fd51" name="ChangeLog" role="doc" />
   <file md5sum="738d18c8f48958cf373246d4147357f0" name="zookeeper-api.php" role="doc" />
   <file md5sum="85ea3d707c1b4c714130e1a0562804be" name="config.m4" role="src" />
   <file md5sum="965efbbb7c5ce55656c13c605f7b4690" name="php_zookeeper.c" role="src" />
   <file md5sum="544aba62acee52e90cdeaa8f1cceee50" name="php_zookeeper.h" role="src" />
   <file md5sum="9772345902c02634b3a8daf8e2cb2c7a" name="php_zookeeper_private.h" role="src" />
   <file md5sum="4de0b1e7e916d5396f996adf1476b696" name="php_zookeeper_session.c" role="src" />
   <file md5sum="28a2e2f9a9676d54f4517b8913720ae1" name="php_zookeeper_session.h" role="src" />
   <file md5sum="b67f10cd2e6b1f6b4369e5a0b85a4bc6" name="zoo_lock.c" role="src" />
   <file md5sum="cfc23f8b4b00ea41377cee135c5948ad" name="zoo_lock.h" role="src" />
   <file md5sum="409c532e44da0ce0caae4ff4f5afd986" name="php_zookeeper_exceptions.c" role="src" />
   <file md5sum="34829c6a237716fd4db8310c5187a4ee" name="php_zookeeper_exceptions.h" role="src" />
   <file md5sum="e33d3014a30e75787f239d34f9ad11f6" name="php_zookeeper_callback.c" role="src" />
   <file md5sum="9e019966bd6358a10eae7b20f0fdfcc5" name="php_zookeeper_callback.h" role="src" />
   <file md5sum="8d23c6129e4ce4715ec330dd701e9c78" name="php_zookeeper_class.h" role="src" />
   <file md5sum="0cc0b231ff922f803067648e1cf6a5e3" name="php_zookeeper_config_class.c" role="src" />
   <file md5sum="2be9b429cee191eca62c8a51ccac497f" name="php_zookeeper_config_class.h" role="src" />
   <file md5sum="0e065e1ee71b7710b7dec2fbd6c04cfc" name="php_zookeeper_stat.c" role="src" />
   <file md5sum="529b8778260276419009a4e2bb3d5778" name="php_zookeeper_stat.h" role="src" />
   <file md5sum="31a4475cdcce6bd778b44d90513f8f1f" name="php_zookeeper_log.c" role="src" />
   <file md5sum="730624e852e127db4377eb6df6473bfd" name="php_zookeeper_log.h" role="src" />
  </dir>
 </contents>
 <dependencies>
  <required>
   <php>
    <min>7.0.0</min>
    <max>8.2.99</max>
   </php>
   <pearinstaller>
    <min>1.4.0b1</min>
   </pearinstaller>
  </required>
 </dependencies>
 <providesextension>zookeeper</providesextension>
 <extsrcrelease />
 <changelog>
  <release>
   <stability>
    <release>alpha</release>
    <api>stable</api>
   </stability>
   <version>
    <release>1.2.0</release>
    <api>0.7.0</api>
   </version>
   <date>2023-02-21</date>
   <notes>
Improvements:
- Make extension compatible with PHP 8.2 (Thanks to Federico J. Álvarez Valero and erikn69, GH PR #55, #56)
   </notes>
  </release>
  <release>
   <stability>
    <release>alpha</release>
    <api>stable</api>
   </stability>
   <version>
    <release>1.0.0</release>
    <api>0.7.0</api>
   </version>
   <date>2021-06-25</date>
   <notes>
Improvements:
- Make extension compatible with Zookeeper 3.6 (Thanks to camporter, GH PR #43)
- Make extension compatible with PHP 8 (Thanks to John P. Bloch, GH PR #44)
   </notes>
  </release>
  <release>
   <stability>
    <release>beta</release>
    <api>alpha</api>
   </stability>
   <version>
    <release>0.7.2</release>
    <api>0.7.0</api>
   </version>
   <date>2019-12-11</date>
   <notes>
Bugs:
- Fix segfault due to double free of global callback data (GH PR #35)
- Optimize callback-related statements
- Fix build error with PHP 7.4 (GH PR #38)
   </notes>
  </release>
  <release>
   <stability>
    <release>alpha</release>
    <api>alpha</api>
   </stability>
   <version>
    <release>0.7.1</release>
    <api>0.7.0</api>
   </version>
   <date>2019-03-08</date>
   <notes>
Bugs:
- Fix segmentation fault after destroying Zookeeper instance (Issue #32)
   </notes>
  </release>
  <release>
   <stability>
    <release>alpha</release>
    <api>alpha</api>
   </stability>
   <version>
    <release>0.7.0</release>
    <api>0.7.0</api>
   </version>
   <date>2019-02-27</date>
   <notes>
Improvements:
- Make parameter &apos;acls&apos; of method &apos;create&apos; optional
- Add static method &apos;dispatch&apos;
- Drop PHP-5 support (Issue #14)
Bugs:
- Fix segmentation fault found in PHP 7.3
   </notes>
  </release>
  <release>
   <stability>
    <release>stable</release>
    <api>alpha</api>
   </stability>
   <version>
    <release>0.6.4</release>
    <api>0.6.0</api>
   </version>
   <date>2019-03-12</date>
   <notes>
Bugs:
- Fix segmentation fault after destroying Zookeeper instance (Issue #32)
   </notes>
  </release>
  <release>
   <stability>
    <release>stable</release>
    <api>alpha</api>
   </stability>
   <version>
    <release>0.6.3</release>
    <api>0.6.0</api>
   </version>
   <date>2019-01-23</date>
   <notes>
Bugs:
- Correct exception message (From &quot;Failed to connect to Zookeeper&quot; to &quot;Failed to initialize ZooKeeper ...&quot;, Issue #29)
- Fix &apos;duplicate symbol _php_zk_config_ce&apos;
- Fix segmentation fault when destroying Zookeeper instance (GH PR #31)
   </notes>
  </release>
  <release>
   <stability>
    <release>beta</release>
    <api>alpha</api>
   </stability>
   <version>
    <release>0.6.2</release>
    <api>0.6.0</api>
   </version>
   <date>2018-07-21</date>
   <notes>
Bugs:
- Fix &apos;undefined symbol: zoo_wgetconfig&apos; with libzookeeper &lt; 3.5 (Issue #22)
   </notes>
  </release>
  <release>
   <stability>
    <release>beta</release>
    <api>alpha</api>
   </stability>
   <version>
    <release>0.6.1</release>
    <api>0.6.0</api>
   </version>
   <date>2018-07-14</date>
   <notes>
Bugs:
- Fix memory leaks
Others:
- Fix symbol conflicts
   </notes>
  </release>
  <release>
   <stability>
    <release>alpha</release>
    <api>alpha</api>
   </stability>
   <version>
    <release>0.6.0</release>
    <api>0.6.0</api>
   </version>
   <date>2018-06-27</date>
   <notes>
Improvements:
- Add class &apos;ZookeeperConfig&apos;
- Add method &apos;getConfig&apos;
- Drop PHP-5 support
   </notes>
  </release>
  <release>
   <stability>
    <release>stable</release>
    <api>stable</api>
   </stability>
   <version>
    <release>0.5.0</release>
    <api>0.5.0</api>
   </version>
   <date>2018-05-14</date>
   <notes>
Improvements:
- Add method &apos;close&apos;
php-zookeeper-0.5.x will be the last series which supports PHP 5.x.
   </notes>
  </release>
  <release>
   <stability>
    <release>beta</release>
    <api>alpha</api>
   </stability>
   <version>
    <release>0.4.1</release>
    <api>0.4.0</api>
   </version>
   <date>2018-05-04</date>
   <notes>
Bugs:
- Fix &apos;Corrupted fcall_info provided to zend_call_function()&apos; (AZ Issue #89, #90)
   </notes>
  </release>
  <release>
   <stability>
    <release>alpha</release>
    <api>alpha</api>
   </stability>
   <version>
    <release>0.4.0</release>
    <api>0.4.0</api>
   </version>
   <date>2017-06-08</date>
   <notes>
Bugs:
- Fix segmentation fault due to improperly implemented threading (PR #13)

Improvements:
- Add function &apos;zookeeper_dispatch&apos;
   </notes>
  </release>
  <release>
   <stability>
    <release>beta</release>
    <api>alpha</api>
   </stability>
   <version>
    <release>0.3.2</release>
    <api>0.3.0</api>
   </version>
   <date>2017-03-31</date>
   <notes>
Bugs:
- Fix duplicate symbols (PR #10)
   </notes>
  </release>
  <release>
   <stability>
    <release>alpha</release>
    <api>alpha</api>
   </stability>
   <version>
    <release>0.3.1</release>
    <api>0.3.0</api>
   </version>
   <date>2017-01-23</date>
   <notes>
Bugs:
- Fix memory leak in method getChildren (Thanks to hulk&lt;hulk.website@gmail.com&gt;, PR #5)
- Fix memory leak in method create (Thanks to Lin Huang, PR #6)
   </notes>
  </release>
  <release>
   <stability>
    <release>alpha</release>
    <api>alpha</api>
   </stability>
   <version>
    <release>0.3.0</release>
    <api>0.3.0</api>
   </version>
   <date>2016-11-18</date>
   <notes>
Bugs:
- Fix session warning with PHP 7.1 (Issue #4)

Improvements:
- Support PHP-7 (PR #1)
- Support exceptions (PR #2)
   </notes>
  </release>
  <release>
   <stability>
    <release>stable</release>
    <api>beta</api>
   </stability>
   <version>
    <release>0.2.3</release>
    <api>0.2.3</api>
   </version>
   <date>2016-11-07</date>
   <notes>
Bugs:
- Fix &apos;Node with null data cause php segfault at Zookeeper::get($path)&apos; (AZ Issue #21)
- Fix &apos;Stat is null when get a node which holds null data&apos; (AZ Issue #29)
- Fix &apos;Wrong type conversion in function call&apos; (Thanks to Dmitry Faleychik&lt;fadimko@gmail.com&gt;, AZ PR #42)
- Fix AZ PR #44 (Thanks to jeff.tang&lt;likeytom@gmail.com&gt;)
- Fix AZ Issue #27 (--with-libdir not honoured, Thanks to Remi Collet)
- Return null after zoo_exists returning 0-length directly (AZ PR #45)

Improvements:
- Respect null&apos;s when passed as values during set(), create(), and get() (Thanks to Ryan Uber&lt;ru@ryanuber.com&gt;, AZ PR #22)
- Make extension compatible with Zookeeper 3.5.0alpha (Thanks to Ryan Uber&lt;ru@ryanuber.com&gt;, AZ PR #28 N #48)
- Display ini entries in `phpinfo()`
   </notes>
  </release>
  <release>
   <stability>
    <release>beta</release>
    <api>beta</api>
   </stability>
   <version>
    <release>0.2.2</release>
    <api>0.2.2</api>
   </version>
   <date>2013-07-30</date>
   <notes>
- PHP 5.4 compatibility
- Sample PHP class for using zookeeper
- Fix NOTCONNECTED_STATE issue
- Various other fixes
   </notes>
  </release>
  <release>
   <stability>
    <release>beta</release>
    <api>beta</api>
   </stability>
   <version>
    <release>0.2.1</release>
    <api>0.2.0</api>
   </version>
   <date>2012-01-13</date>
   <notes>
- Package up missed source files
   </notes>
  </release>
  <release>
   <stability>
    <release>beta</release>
    <api>beta</api>
   </stability>
   <version>
    <release>0.2.0</release>
    <api>0.2.0</api>
   </version>
   <date>2012-01-12</date>
   <notes>
- Added session handler support
- Added connect() and delete methods
- Bug fixes
   </notes>
  </release>
  <release>
   <stability>
    <release>beta</release>
    <api>beta</api>
   </stability>
   <version>
    <release>0.1.0</release>
    <api>0.1.0</api>
   </version>
   <date>2009-10-15</date>
   <notes>
- Initial PECL release
   </notes>
  </release>
 </changelog>
</package>
