<?xml version="1.0" encoding="UTF-8"?>
<package packagerversion="1.10.12" version="2.0" xmlns="http://pear.php.net/dtd/package-2.0" xmlns:tasks="http://pear.php.net/dtd/tasks-1.0" xmlns:xsi="http://www.w3.org/2001/XMLSchema-instance" xsi:schemaLocation="http://pear.php.net/dtd/tasks-1.0     http://pear.php.net/dtd/tasks-1.0.xsd     http://pear.php.net/dtd/package-2.0     http://pear.php.net/dtd/package-2.0.xsd">
 <name>ice</name>
 <channel>pecl.php.net</channel>
 <summary>Simple and fast PHP framework</summary>
 <description>Ice is a PHP framework frozen in C extension.</description>
 <lead>
  <name>Mariusz Laczak</name>
  <user>mruz</user>
  <email>mruz@php.net</email>
  <active>yes</active>
 </lead>
 <date>2021-02-12</date>
 <time>08:16:36</time>
 <version>
  <release>1.8.0alpha2</release>
  <api>1.8.0</api>
 </version>
 <stability>
  <release>alpha</release>
  <api>stable</api>
 </stability>
 <license uri="https://www.iceframework.org/license">BSD-3-Clause</license>
 <notes>
- PHP 7.1, drop support, update phpunit to v8
- Update zephir parser to 1.3.5
- Zephir, use zephir-php8 branch
- Pdo, fix associative array in order by
- PHP 7.2 and 7.3, drop support
- Tests, fix get related count and filter
- Version, remove hyphen fix #292
 </notes>
 <contents>
  <dir baseinstalldir="/" name="/">
   <file baseinstalldir="/" md5sum="979c9f4983ca7138ebb675fa00e51363" name="ice/arr.zep.c" role="src" />
   <file baseinstalldir="/" md5sum="f49a67cff2b20ecceb60f649933dc867" name="ice/arr.zep.h" role="src" />
   <file baseinstalldir="/" md5sum="3d8260fa6d0c3104ac6559234285b11e" name="ice/assets.zep.c" role="src" />
   <file baseinstalldir="/" md5sum="b06d33c23ae4d196e36093e92fcf3167" name="ice/assets.zep.h" role="src" />
   <file baseinstalldir="/" md5sum="9b38f064bd38946d21b39e3f87f5deb3" name="ice/auth.zep.c" role="src" />
   <file baseinstalldir="/" md5sum="9c39018cb4134ad19736d3142c48456e" name="ice/auth.zep.h" role="src" />
   <file baseinstalldir="/" md5sum="6ab752833ece14cf60f6ceba008acc5d" name="ice/config.zep.c" role="src" />
   <file baseinstalldir="/" md5sum="7d0381ee2d373f685cdb4937bc7f87a6" name="ice/config.zep.h" role="src" />
   <file baseinstalldir="/" md5sum="50e82aa8c0c8e4dd6a182977333ca1df" name="ice/cookies.zep.c" role="src" />
   <file baseinstalldir="/" md5sum="0158d97f6f2dad4725fa290cb49a3d83" name="ice/cookies.zep.h" role="src" />
   <file baseinstalldir="/" md5sum="d58535bd1d40db59208f55a198b4ec3f" name="ice/crypt.zep.c" role="src" />
   <file baseinstalldir="/" md5sum="e3ed4f0f7bbc4369739dc507a8b523f2" name="ice/crypt.zep.h" role="src" />
   <file baseinstalldir="/" md5sum="be0ec48f1683d209080564cd8cb1e8c2" name="ice/db.zep.c" role="src" />
   <file baseinstalldir="/" md5sum="4b663db203d11a873da4b9e7100bee87" name="ice/db.zep.h" role="src" />
   <file baseinstalldir="/" md5sum="d5dafc676faa00d06d6679b93d5834ac" name="ice/di.zep.c" role="src" />
   <file baseinstalldir="/" md5sum="393fd428469e89ed3e5da1b2b97e36d0" name="ice/di.zep.h" role="src" />
   <file baseinstalldir="/" md5sum="126b4f1bead1d5466ee7d17e0f2a4606" name="ice/dispatcher.zep.c" role="src" />
   <file baseinstalldir="/" md5sum="9461646b3863ed19b036244512f5fd97" name="ice/dispatcher.zep.h" role="src" />
   <file baseinstalldir="/" md5sum="d90c0fe97dda2ab5927e8a090bd37ce0" name="ice/dump.zep.c" role="src" />
   <file baseinstalldir="/" md5sum="4dc7c98d91428685adff1afea8dee162" name="ice/dump.zep.h" role="src" />
   <file baseinstalldir="/" md5sum="c990f9d60edc10174f61529e4aad9a8f" name="ice/exception.zep.c" role="src" />
   <file baseinstalldir="/" md5sum="3aac3d761581bdb442129dd1dad04160" name="ice/exception.zep.h" role="src" />
   <file baseinstalldir="/" md5sum="7f2d1a9ee48146bcd150ba7007142ebb" name="ice/filter.zep.c" role="src" />
   <file baseinstalldir="/" md5sum="721bda903a1824ac826343d40beebf47" name="ice/filter.zep.h" role="src" />
   <file baseinstalldir="/" md5sum="7f7be7b2f49b43dee82ac3b8c84bd867" name="ice/flash.zep.c" role="src" />
   <file baseinstalldir="/" md5sum="c5381438c487962e3ef53fae4bef9d2b" name="ice/flash.zep.h" role="src" />
   <file baseinstalldir="/" md5sum="1965de9eab161c8a0842bceb7000824d" name="ice/i18n.zep.c" role="src" />
   <file baseinstalldir="/" md5sum="63ef4917c4a53ce3ea1d8b7de9dbe679" name="ice/i18n.zep.h" role="src" />
   <file baseinstalldir="/" md5sum="c2b53b3ff1f73e4642f057566a53e283" name="ice/image.zep.c" role="src" />
   <file baseinstalldir="/" md5sum="bbee22117ff1aeaab9e4f5a946c800b5" name="ice/image.zep.h" role="src" />
   <file baseinstalldir="/" md5sum="9d4794293a0ccbad3e2625ac881d7a83" name="ice/loader.zep.c" role="src" />
   <file baseinstalldir="/" md5sum="2cb328fff0f80c0ffb1a32672e8ba3a8" name="ice/loader.zep.h" role="src" />
   <file baseinstalldir="/" md5sum="cbdb1488327c773f862ebc49e281d81e" name="ice/log.zep.c" role="src" />
   <file baseinstalldir="/" md5sum="14352455ca442afb8854068d7273d1d0" name="ice/log.zep.h" role="src" />
   <file baseinstalldir="/" md5sum="4a198c018cda19ac3d4b99fb29698104" name="ice/pagination.zep.c" role="src" />
   <file baseinstalldir="/" md5sum="bdf0c3e786f93719dd23d58971d2f43e" name="ice/pagination.zep.h" role="src" />
   <file baseinstalldir="/" md5sum="31809c93cc58de383e685faf524d9a61" name="ice/session.zep.c" role="src" />
   <file baseinstalldir="/" md5sum="9b90e3ba0ebe052c3f3dff83df16e69b" name="ice/session.zep.h" role="src" />
   <file baseinstalldir="/" md5sum="71cc78e969acb3cbeeb30c336501130f" name="ice/tag.zep.c" role="src" />
   <file baseinstalldir="/" md5sum="60e961c2854abcef5fb4d6759b7da313" name="ice/tag.zep.h" role="src" />
   <file baseinstalldir="/" md5sum="64bb91d0839996146163b9293d0782fe" name="ice/text.zep.c" role="src" />
   <file baseinstalldir="/" md5sum="7cb514b6ad9f48fcd06ef05310f6d5a8" name="ice/text.zep.h" role="src" />
   <file baseinstalldir="/" md5sum="81b85f7254225f7e44035319826fb321" name="ice/validation.zep.c" role="src" />
   <file baseinstalldir="/" md5sum="36dc45efe05498502bdc2eb4e29f5a85" name="ice/validation.zep.h" role="src" />
   <file baseinstalldir="/" md5sum="9710fe0261738e05d1848f1c358a8edc" name="ice/version.zep.c" role="src" />
   <file baseinstalldir="/" md5sum="f1d0a4c4c24e2be78218c330383d3ca1" name="ice/version.zep.h" role="src" />
   <file baseinstalldir="/" md5sum="dbe3dd423fea4c3c4f6494ea4ac59034" name="ice/auth/driver.zep.c" role="src" />
   <file baseinstalldir="/" md5sum="3d0cf065ab1d3db768773e06f90a4930" name="ice/auth/driver.zep.h" role="src" />
   <file baseinstalldir="/" md5sum="3d47608eaec40fc67684c2740d606d8a" name="ice/auth/social.zep.c" role="src" />
   <file baseinstalldir="/" md5sum="51904a0fca0d3391a60809bdbc5b282d" name="ice/auth/social.zep.h" role="src" />
   <file baseinstalldir="/" md5sum="b35e28435ba6ba02cdf2ec581a987853" name="ice/auth/driver/db.zep.c" role="src" />
   <file baseinstalldir="/" md5sum="c31f26b0cef0554c56488aebe8577635" name="ice/auth/driver/db.zep.h" role="src" />
   <file baseinstalldir="/" md5sum="6779dcb3d1431d7322c978ed5197869b" name="ice/auth/driver/driverinterface.zep.c" role="src" />
   <file baseinstalldir="/" md5sum="a4da82bdb36f6c457e16f575c6d8625a" name="ice/auth/driver/driverinterface.zep.h" role="src" />
   <file baseinstalldir="/" md5sum="90948d16f939faa6174cbc27ec70c0f6" name="ice/auth/driver/file.zep.c" role="src" />
   <file baseinstalldir="/" md5sum="f78a9eaafe5e4504edb170d59651acae" name="ice/auth/driver/file.zep.h" role="src" />
   <file baseinstalldir="/" md5sum="1176f83e218322c6c25b98a4773912f0" name="ice/auth/driver/model/roles.zep.c" role="src" />
   <file baseinstalldir="/" md5sum="7e4bf159df2c2cde46b003b7022dcb40" name="ice/auth/driver/model/roles.zep.h" role="src" />
   <file baseinstalldir="/" md5sum="4fc9d24e20c3634de9c428bc9eaeaecc" name="ice/auth/driver/model/users.zep.c" role="src" />
   <file baseinstalldir="/" md5sum="eb4e590d5634130b9866ca07d0efc3dd" name="ice/auth/driver/model/users.zep.h" role="src" />
   <file baseinstalldir="/" md5sum="0a1ffc68615249ba0e7fadaf0efa278d" name="ice/auth/driver/model/roles/users.zep.c" role="src" />
   <file baseinstalldir="/" md5sum="5eee4ea31d6f61fa0f4fb5cbf9acf754" name="ice/auth/driver/model/roles/users.zep.h" role="src" />
   <file baseinstalldir="/" md5sum="4c4aa047754834e8277452245ec64f8e" name="ice/auth/driver/model/users/social.zep.c" role="src" />
   <file baseinstalldir="/" md5sum="b0f71aeb6abb0dad982f9f0fbd0ae6f2" name="ice/auth/driver/model/users/social.zep.h" role="src" />
   <file baseinstalldir="/" md5sum="42b7170154272877f090dbefa4df7755" name="ice/auth/driver/model/users/tokens.zep.c" role="src" />
   <file baseinstalldir="/" md5sum="41981153489741a2abf6a1830c923cc8" name="ice/auth/driver/model/users/tokens.zep.h" role="src" />
   <file baseinstalldir="/" md5sum="b1f808196e86efd5fd74ff18a6ab219b" name="ice/auth/social/adapter.zep.c" role="src" />
   <file baseinstalldir="/" md5sum="7c0b1da06fbc4e012514b83be59dd4b7" name="ice/auth/social/adapter.zep.h" role="src" />
   <file baseinstalldir="/" md5sum="5b7d286160302a9cfea5601377d87e76" name="ice/auth/social/facebook.zep.c" role="src" />
   <file baseinstalldir="/" md5sum="983414e45966ec7475c8e26e881d85d5" name="ice/auth/social/facebook.zep.h" role="src" />
   <file baseinstalldir="/" md5sum="e4dd7e8f74025d9210154a708018df54" name="ice/auth/social/google.zep.c" role="src" />
   <file baseinstalldir="/" md5sum="3ef451bf561af67494052053951b193f" name="ice/auth/social/google.zep.h" role="src" />
   <file baseinstalldir="/" md5sum="d5092c722571263ab7f26dc4ff7ce0d1" name="ice/auth/social/socialinterface.zep.c" role="src" />
   <file baseinstalldir="/" md5sum="c9cafda0732536c5c56b7bc77b919121" name="ice/auth/social/socialinterface.zep.h" role="src" />
   <file baseinstalldir="/" md5sum="9087b6ffb0b077418bc38a440147a406" name="ice/auth/social/twitter.zep.c" role="src" />
   <file baseinstalldir="/" md5sum="9e04aa9d408763da6800f2079f443046" name="ice/auth/social/twitter.zep.h" role="src" />
   <file baseinstalldir="/" md5sum="d47fd1485e682da0da4291e7f5f498e4" name="ice/cli/console.zep.c" role="src" />
   <file baseinstalldir="/" md5sum="8caf9a7e4aa3d6905576596c33a7feac" name="ice/cli/console.zep.h" role="src" />
   <file baseinstalldir="/" md5sum="d5c151e207caf0af48fa21a2af6b6342" name="ice/cli/dispatcher.zep.c" role="src" />
   <file baseinstalldir="/" md5sum="0e0020249277ce70181f61b6f902ca14" name="ice/cli/dispatcher.zep.h" role="src" />
   <file baseinstalldir="/" md5sum="5cd17ee825d5b15eb57b067f5fad0c65" name="ice/cli/router.zep.c" role="src" />
   <file baseinstalldir="/" md5sum="40eb5997175bc3df0d24560ffcb573aa" name="ice/cli/router.zep.h" role="src" />
   <file baseinstalldir="/" md5sum="31b069fcb57810cf3fac5ccd161f2772" name="ice/cli/task.zep.c" role="src" />
   <file baseinstalldir="/" md5sum="60ecbbfbbd86b93b5354c4fe2bf2a74f" name="ice/cli/task.zep.h" role="src" />
   <file baseinstalldir="/" md5sum="44405088459896f725abae262d592b2d" name="ice/cli/websocket/client.zep.c" role="src" />
   <file baseinstalldir="/" md5sum="893f77d4e51ca68f59a08cf129b30bc8" name="ice/cli/websocket/client.zep.h" role="src" />
   <file baseinstalldir="/" md5sum="d0406908c600a06789c9ec434bb9bcd8" name="ice/cli/websocket/server.zep.c" role="src" />
   <file baseinstalldir="/" md5sum="2e74fe33612bb82cfd18158cf750f5df" name="ice/cli/websocket/server.zep.h" role="src" />
   <file baseinstalldir="/" md5sum="321f70ab382c8fa9b6040121bc459959" name="ice/cli/websocket/websocket.zep.c" role="src" />
   <file baseinstalldir="/" md5sum="b25e4fd108b60373b9f5f09ec44a8b82" name="ice/cli/websocket/websocket.zep.h" role="src" />
   <file baseinstalldir="/" md5sum="3fc9c16dd6633270e48aaebb74363c11" name="ice/config/env.zep.c" role="src" />
   <file baseinstalldir="/" md5sum="adbcbb253000f79f9b7e913447eea3b4" name="ice/config/env.zep.h" role="src" />
   <file baseinstalldir="/" md5sum="f98a3eb4b634f378328c7c4effc54076" name="ice/config/ini.zep.c" role="src" />
   <file baseinstalldir="/" md5sum="f8d83ebc56ed4e9dad3f99969dadcb65" name="ice/config/ini.zep.h" role="src" />
   <file baseinstalldir="/" md5sum="f5cb8eee1ed6799d2ac0a4ab880b3276" name="ice/config/json.zep.c" role="src" />
   <file baseinstalldir="/" md5sum="131e1bb9b48002b64438751f88b658c6" name="ice/config/json.zep.h" role="src" />
   <file baseinstalldir="/" md5sum="b0402f7aa4568d5553253b5ca58ff2de" name="ice/db/dbinterface.zep.c" role="src" />
   <file baseinstalldir="/" md5sum="740b4ce1317abef77f07027ecbaa344d" name="ice/db/dbinterface.zep.h" role="src" />
   <file baseinstalldir="/" md5sum="3ebb6d7d48ba6c6b56fb1085ee185c4f" name="ice/db/driver/mongodb.zep.c" role="src" />
   <file baseinstalldir="/" md5sum="6f0163ee56092a51505dd28b61e6a83e" name="ice/db/driver/mongodb.zep.h" role="src" />
   <file baseinstalldir="/" md5sum="d9866a67a55ef9eb69f71cb5e69bd537" name="ice/db/driver/pdo.zep.c" role="src" />
   <file baseinstalldir="/" md5sum="5148dd2d02a35dac5232737addc3d129" name="ice/db/driver/pdo.zep.h" role="src" />
   <file baseinstalldir="/" md5sum="312dddb2f34d8ff7f6563b6f8d0de9ae" name="ice/di/access.zep.c" role="src" />
   <file baseinstalldir="/" md5sum="96ff1477fc562abf8eb3bee633265853" name="ice/di/access.zep.h" role="src" />
   <file baseinstalldir="/" md5sum="b08101acde60cac45d57181f39567d96" name="ice/filter/css.zep.c" role="src" />
   <file baseinstalldir="/" md5sum="e7bb1e1202db2c43c615ded4fad435ca" name="ice/filter/css.zep.h" role="src" />
   <file baseinstalldir="/" md5sum="24a831ba137584a35fb4f08d7ac0f66e" name="ice/filter/js.zep.c" role="src" />
   <file baseinstalldir="/" md5sum="a13c5459b5f3f9fa0d5f0bd78cc557a9" name="ice/filter/js.zep.h" role="src" />
   <file baseinstalldir="/" md5sum="68a10cca8f085349ad58fdcecb6360db" name="ice/http/request.zep.c" role="src" />
   <file baseinstalldir="/" md5sum="8edf18abceec77fe066c280170fc6b63" name="ice/http/request.zep.h" role="src" />
   <file baseinstalldir="/" md5sum="5ffc6f32d570a45f4dcd3de9ee49031c" name="ice/http/response.zep.c" role="src" />
   <file baseinstalldir="/" md5sum="236194e851b5bd8be2ca5cb794f62985" name="ice/http/response.zep.h" role="src" />
   <file baseinstalldir="/" md5sum="4185a4a91bf0cf6195905e89d18b9c66" name="ice/http/request/requestinterface.zep.c" role="src" />
   <file baseinstalldir="/" md5sum="4eadf6d414a9eaac54d87532024b9238" name="ice/http/request/requestinterface.zep.h" role="src" />
   <file baseinstalldir="/" md5sum="318af8fde6e1bb6f19c5ce7b63bc9133" name="ice/http/response/headers.zep.c" role="src" />
   <file baseinstalldir="/" md5sum="1244120f8234633ac5ce5fb8e415ffd3" name="ice/http/response/headers.zep.h" role="src" />
   <file baseinstalldir="/" md5sum="33008085b73fb5c4d3042aa216252e37" name="ice/http/response/headersinterface.zep.c" role="src" />
   <file baseinstalldir="/" md5sum="b2324b2dc90aec771eea53e14d876ea5" name="ice/http/response/headersinterface.zep.h" role="src" />
   <file baseinstalldir="/" md5sum="d92253d2d3c3bf84817273ea90465afe" name="ice/http/response/responseinterface.zep.c" role="src" />
   <file baseinstalldir="/" md5sum="ee44232c25fb1ed4707af58f38172012" name="ice/http/response/responseinterface.zep.h" role="src" />
   <file baseinstalldir="/" md5sum="20d03dfc2672a4ad234bc8096b5c04da" name="ice/i18n/plural/arabic.zep.c" role="src" />
   <file baseinstalldir="/" md5sum="470e55e08d81f6b7c664faa46a8488c2" name="ice/i18n/plural/arabic.zep.h" role="src" />
   <file baseinstalldir="/" md5sum="247b706442e743a5678d2aee12624820" name="ice/i18n/plural/balkan.zep.c" role="src" />
   <file baseinstalldir="/" md5sum="f822ddb6538c203d4d6cac7a4dd93681" name="ice/i18n/plural/balkan.zep.h" role="src" />
   <file baseinstalldir="/" md5sum="97a49ecd4521d504aa85b568b7d1a118" name="ice/i18n/plural/czech.zep.c" role="src" />
   <file baseinstalldir="/" md5sum="04441dbc48dc2aa173210097f2833645" name="ice/i18n/plural/czech.zep.h" role="src" />
   <file baseinstalldir="/" md5sum="ce9ebcdd17b69a622ef47b3a48c25e5f" name="ice/i18n/plural/french.zep.c" role="src" />
   <file baseinstalldir="/" md5sum="19ab7f1a50eef33018abaf0f6fab5f0d" name="ice/i18n/plural/french.zep.h" role="src" />
   <file baseinstalldir="/" md5sum="0d693cf912cbde498726bc6ef78a40e3" name="ice/i18n/plural/none.zep.c" role="src" />
   <file baseinstalldir="/" md5sum="7567fbd0873b46e862914d4564d69751" name="ice/i18n/plural/none.zep.h" role="src" />
   <file baseinstalldir="/" md5sum="a39e218c82821ab24f77275cb8f5e054" name="ice/i18n/plural/one.zep.c" role="src" />
   <file baseinstalldir="/" md5sum="6fa9f6e0d5533b9ee8df2835798aff07" name="ice/i18n/plural/one.zep.h" role="src" />
   <file baseinstalldir="/" md5sum="3b0f2609df1df2db12b25753d67a78de" name="ice/i18n/plural/pluralinterface.zep.c" role="src" />
   <file baseinstalldir="/" md5sum="30058ea9f3058db7c56c926982b80861" name="ice/i18n/plural/pluralinterface.zep.h" role="src" />
   <file baseinstalldir="/" md5sum="2f9e25e9369de708f8e964d2dc75ccac" name="ice/i18n/plural/polish.zep.c" role="src" />
   <file baseinstalldir="/" md5sum="7a7f3c77d2ab7d06eb40028dd991fcc5" name="ice/i18n/plural/polish.zep.h" role="src" />
   <file baseinstalldir="/" md5sum="cac0531b4711ef4946fab25fad923604" name="ice/i18n/plural/romanian.zep.c" role="src" />
   <file baseinstalldir="/" md5sum="7858e85310b8ca01bea05d7bcf3ddf35" name="ice/i18n/plural/romanian.zep.h" role="src" />
   <file baseinstalldir="/" md5sum="4653ad1208eeff3458419933ea8eff50" name="ice/i18n/plural/two.zep.c" role="src" />
   <file baseinstalldir="/" md5sum="51bcdc66a4c5e6065c88ad137c7e23df" name="ice/i18n/plural/two.zep.h" role="src" />
   <file baseinstalldir="/" md5sum="ed8290cd185248fc6fb84bfdb2fd2ba8" name="ice/i18n/plural/zero.zep.c" role="src" />
   <file baseinstalldir="/" md5sum="50a18aa7a840daa7d9685d85568162be" name="ice/i18n/plural/zero.zep.h" role="src" />
   <file baseinstalldir="/" md5sum="4fbaf9cabc7c3c8c4d1d269bdc645b3d" name="ice/image/gd.zep.c" role="src" />
   <file baseinstalldir="/" md5sum="c20cf81aa9eedda014e9d54cdc49e8a8" name="ice/image/gd.zep.h" role="src" />
   <file baseinstalldir="/" md5sum="25fc5136bda609230bc2605e3d5e9860" name="ice/log/driver.zep.c" role="src" />
   <file baseinstalldir="/" md5sum="8ac52225bb283f8447dd2a91af79384a" name="ice/log/driver.zep.h" role="src" />
   <file baseinstalldir="/" md5sum="c7b06d6aa9a44818cd4f02f47e4ed197" name="ice/log/loggerinterface.zep.c" role="src" />
   <file baseinstalldir="/" md5sum="0a1dfd26e91d471ccec730b2822668d3" name="ice/log/loggerinterface.zep.h" role="src" />
   <file baseinstalldir="/" md5sum="54a9d22983844ef28f381da8ff5c8fa0" name="ice/log/driver/file.zep.c" role="src" />
   <file baseinstalldir="/" md5sum="28a0c4222d609908bf42c9cae0d5a7f9" name="ice/log/driver/file.zep.h" role="src" />
   <file baseinstalldir="/" md5sum="e2c5e7e73bf62574327fd53b04ef6787" name="ice/mvc/app.zep.c" role="src" />
   <file baseinstalldir="/" md5sum="59e2ac910a6e8935f5789d0350c0bf58" name="ice/mvc/app.zep.h" role="src" />
   <file baseinstalldir="/" md5sum="d9aef3e7c786d669fd919516199bee44" name="ice/mvc/controller.zep.c" role="src" />
   <file baseinstalldir="/" md5sum="25ba3892a02a67e2b82f22fa52399203" name="ice/mvc/controller.zep.h" role="src" />
   <file baseinstalldir="/" md5sum="2ac611eab7c224a2b03f5c904246ecdc" name="ice/mvc/dispatcher.zep.c" role="src" />
   <file baseinstalldir="/" md5sum="65e2652fd95e4dcc4294eccd7c5a7f9f" name="ice/mvc/dispatcher.zep.h" role="src" />
   <file baseinstalldir="/" md5sum="eeabf400b6565eed2455396b40c87d40" name="ice/mvc/fastroute.zep.c" role="src" />
   <file baseinstalldir="/" md5sum="654d8676cc343fd679a68aeb5cac9d32" name="ice/mvc/fastroute.zep.h" role="src" />
   <file baseinstalldir="/" md5sum="8322e06eb97e09c24a91caccb4776e2c" name="ice/mvc/fastrouter.zep.c" role="src" />
   <file baseinstalldir="/" md5sum="82c8ebd5fd2e4ff929f970b2b291ccec" name="ice/mvc/fastrouter.zep.h" role="src" />
   <file baseinstalldir="/" md5sum="027288786d508a2d00028110b57fef06" name="ice/mvc/model.zep.c" role="src" />
   <file baseinstalldir="/" md5sum="2d6e81c79b40f9432d78ce8d14885868" name="ice/mvc/model.zep.h" role="src" />
   <file baseinstalldir="/" md5sum="fdeb9ddea492e0346643112309b2b367" name="ice/mvc/moduleinterface.zep.c" role="src" />
   <file baseinstalldir="/" md5sum="f09562ae7a5c2aa88e18fa5cd6bf3390" name="ice/mvc/moduleinterface.zep.h" role="src" />
   <file baseinstalldir="/" md5sum="c3539489d3ca87208302ef4275ccffba" name="ice/mvc/route.zep.c" role="src" />
   <file baseinstalldir="/" md5sum="713cfddde7b667efa648213efca9ad46" name="ice/mvc/route.zep.h" role="src" />
   <file baseinstalldir="/" md5sum="96529a8b92c2501cde9d32c622043229" name="ice/mvc/router.zep.c" role="src" />
   <file baseinstalldir="/" md5sum="29b59a503fe0e5db366e1e2331bbbe64" name="ice/mvc/router.zep.h" role="src" />
   <file baseinstalldir="/" md5sum="daa8c6557097ba11e6ff1b5e54d88aa7" name="ice/mvc/service.zep.c" role="src" />
   <file baseinstalldir="/" md5sum="0fbbfc11b7512bd7d166e762cc3a63cc" name="ice/mvc/service.zep.h" role="src" />
   <file baseinstalldir="/" md5sum="c561019175129296fd4e44d86d7d5fa3" name="ice/mvc/url.zep.c" role="src" />
   <file baseinstalldir="/" md5sum="e2d9ffee47690382ce0008aaa99ce664" name="ice/mvc/url.zep.h" role="src" />
   <file baseinstalldir="/" md5sum="6feee34836474718ae92362659b874ca" name="ice/mvc/view.zep.c" role="src" />
   <file baseinstalldir="/" md5sum="4202ced5043744050dea324273530fe9" name="ice/mvc/view.zep.h" role="src" />
   <file baseinstalldir="/" md5sum="63705a1c34c260cfc0277a622d259d87" name="ice/mvc/route/collector.zep.c" role="src" />
   <file baseinstalldir="/" md5sum="c7e02b6d359e1bdeaaaddef796b2c06f" name="ice/mvc/route/collector.zep.h" role="src" />
   <file baseinstalldir="/" md5sum="655620dab009cf75855cfcc60184857d" name="ice/mvc/route/datagenerator/datageneratorinterface.zep.c" role="src" />
   <file baseinstalldir="/" md5sum="c213c184d9ef298ccd0db67ba5dc9327" name="ice/mvc/route/datagenerator/datageneratorinterface.zep.h" role="src" />
   <file baseinstalldir="/" md5sum="70fb3cc4bd19c3a2becab27c16d92981" name="ice/mvc/route/datagenerator/groupcount.zep.c" role="src" />
   <file baseinstalldir="/" md5sum="88a7405a2040ebdf509f1c07be9ee005" name="ice/mvc/route/datagenerator/groupcount.zep.h" role="src" />
   <file baseinstalldir="/" md5sum="2e94dd4752e4a9cd2d81bf0fcfebf25c" name="ice/mvc/route/datagenerator/regex.zep.c" role="src" />
   <file baseinstalldir="/" md5sum="5b3985ac2d7ed40179c6d6589af49bb3" name="ice/mvc/route/datagenerator/regex.zep.h" role="src" />
   <file baseinstalldir="/" md5sum="792c7e3482125a41589a254775bb28b0" name="ice/mvc/route/dispatcher/dispatcherinterface.zep.c" role="src" />
   <file baseinstalldir="/" md5sum="882328413db093a73deb81dff2de0241" name="ice/mvc/route/dispatcher/dispatcherinterface.zep.h" role="src" />
   <file baseinstalldir="/" md5sum="059a68f6acea86b9ce423edb3a6ab5ab" name="ice/mvc/route/dispatcher/groupcount.zep.c" role="src" />
   <file baseinstalldir="/" md5sum="bcb230b30e9dd29e91d2accd7fcbb4f9" name="ice/mvc/route/dispatcher/groupcount.zep.h" role="src" />
   <file baseinstalldir="/" md5sum="6b2e463d2e1844828380884566d07779" name="ice/mvc/route/dispatcher/regex.zep.c" role="src" />
   <file baseinstalldir="/" md5sum="b5d0c34b44bb2fd5fe0543d255f650ea" name="ice/mvc/route/dispatcher/regex.zep.h" role="src" />
   <file baseinstalldir="/" md5sum="f899824efaac1df4c3f15b11833620ce" name="ice/mvc/route/parser/parserinterface.zep.c" role="src" />
   <file baseinstalldir="/" md5sum="881c4c0f38e9485ed8f6d9e06ef66f66" name="ice/mvc/route/parser/parserinterface.zep.h" role="src" />
   <file baseinstalldir="/" md5sum="c3ebfec7937c71617f482c2829f40b0f" name="ice/mvc/route/parser/std.zep.c" role="src" />
   <file baseinstalldir="/" md5sum="f1f712ca88875e1448ce0a4689a4ff3b" name="ice/mvc/route/parser/std.zep.h" role="src" />
   <file baseinstalldir="/" md5sum="cc7c12bee9867ba563b6d5b5b39601fa" name="ice/mvc/view/engine.zep.c" role="src" />
   <file baseinstalldir="/" md5sum="141e48b0e24aa4a84061c94cb3f59282" name="ice/mvc/view/engine.zep.h" role="src" />
   <file baseinstalldir="/" md5sum="a21b0005a4f3187bd48f771c43a03538" name="ice/mvc/view/viewinterface.zep.c" role="src" />
   <file baseinstalldir="/" md5sum="1f86c40deb9038a4eb09b0f6d30ad66f" name="ice/mvc/view/viewinterface.zep.h" role="src" />
   <file baseinstalldir="/" md5sum="cd9dc0dc57185ec142137a89e6f9d92a" name="ice/mvc/view/engine/engineinterface.zep.c" role="src" />
   <file baseinstalldir="/" md5sum="d31a73ae466cad69f91b0c71793c14ba" name="ice/mvc/view/engine/engineinterface.zep.h" role="src" />
   <file baseinstalldir="/" md5sum="09463f6328685cc45ac0ba3a3c0aebd2" name="ice/mvc/view/engine/php.zep.c" role="src" />
   <file baseinstalldir="/" md5sum="2e8036c5738d8cdf3b89acba22290eb5" name="ice/mvc/view/engine/php.zep.h" role="src" />
   <file baseinstalldir="/" md5sum="720ec0491c07dbe6753fa414feafe930" name="ice/mvc/view/engine/sleet.zep.c" role="src" />
   <file baseinstalldir="/" md5sum="08089d226779b646ebbce9e333406403" name="ice/mvc/view/engine/sleet.zep.h" role="src" />
   <file baseinstalldir="/" md5sum="c6575d0bcd5328362b6d6683c87c856a" name="ice/mvc/view/engine/sleet/compiler.zep.c" role="src" />
   <file baseinstalldir="/" md5sum="2e1295444ed048fa755ad2fb2ad7be6a" name="ice/mvc/view/engine/sleet/compiler.zep.h" role="src" />
   <file baseinstalldir="/" md5sum="901c70de1e89c8070ce91f21a97c40e5" name="ice/mvc/view/engine/sleet/parser.zep.c" role="src" />
   <file baseinstalldir="/" md5sum="2d063914b6254c92dea80b5395f01905" name="ice/mvc/view/engine/sleet/parser.zep.h" role="src" />
   <file baseinstalldir="/" md5sum="4c68564ddd80ce59d373ba22c28c31fe" name="ice/validation/validator.zep.c" role="src" />
   <file baseinstalldir="/" md5sum="fc31e74b2cc1b9e1502106b1d5394948" name="ice/validation/validator.zep.h" role="src" />
   <file baseinstalldir="/" md5sum="946f38faacffed9fa51e6b4b80008395" name="ice/validation/validator/alnum.zep.c" role="src" />
   <file baseinstalldir="/" md5sum="05067fc4f6e0b9bb30b28fb108eaf4b0" name="ice/validation/validator/alnum.zep.h" role="src" />
   <file baseinstalldir="/" md5sum="63d4b7e1a5646b4a08ff7708af0b3f9b" name="ice/validation/validator/alpha.zep.c" role="src" />
   <file baseinstalldir="/" md5sum="287356855dca26dacae2aa3a074d7720" name="ice/validation/validator/alpha.zep.h" role="src" />
   <file baseinstalldir="/" md5sum="cc549bc33b1aa33c8233127f12b7d46d" name="ice/validation/validator/between.zep.c" role="src" />
   <file baseinstalldir="/" md5sum="12c57ecfa1d33994a4cbb33d28e34959" name="ice/validation/validator/between.zep.h" role="src" />
   <file baseinstalldir="/" md5sum="c82478fd520f712b8a8be894bede821a" name="ice/validation/validator/digit.zep.c" role="src" />
   <file baseinstalldir="/" md5sum="a734d26ffbc61b622922917d0f026537" name="ice/validation/validator/digit.zep.h" role="src" />
   <file baseinstalldir="/" md5sum="ed5f942d14a2ab239a781bd9b03b7477" name="ice/validation/validator/email.zep.c" role="src" />
   <file baseinstalldir="/" md5sum="3c05b22217a998f60ad3200d498cf30b" name="ice/validation/validator/email.zep.h" role="src" />
   <file baseinstalldir="/" md5sum="8b51961204a685f009422341f941c942" name="ice/validation/validator/exists.zep.c" role="src" />
   <file baseinstalldir="/" md5sum="050746a23034912de6ca164033f0dd19" name="ice/validation/validator/exists.zep.h" role="src" />
   <file baseinstalldir="/" md5sum="8671f6b77099fb789f630fb88fc1c34b" name="ice/validation/validator/file.zep.c" role="src" />
   <file baseinstalldir="/" md5sum="3ab579299fa021ef4067b074dc0389f0" name="ice/validation/validator/file.zep.h" role="src" />
   <file baseinstalldir="/" md5sum="add098dd415f5a72eec42f30a5b940fd" name="ice/validation/validator/in.zep.c" role="src" />
   <file baseinstalldir="/" md5sum="f4307181af040da93bdf2cd8f671843f" name="ice/validation/validator/in.zep.h" role="src" />
   <file baseinstalldir="/" md5sum="db6c2f4d0acfc4c8d228f9162ad8740a" name="ice/validation/validator/length.zep.c" role="src" />
   <file baseinstalldir="/" md5sum="87a617ac323ea3177fad83e0c3c05ea7" name="ice/validation/validator/length.zep.h" role="src" />
   <file baseinstalldir="/" md5sum="1e12a1aea1a61030b37343eb4bd2192c" name="ice/validation/validator/notin.zep.c" role="src" />
   <file baseinstalldir="/" md5sum="3988fa142b8dc7e9b8e9d78173c3a1b6" name="ice/validation/validator/notin.zep.h" role="src" />
   <file baseinstalldir="/" md5sum="8259efa9def9d34199d7751e522256de" name="ice/validation/validator/regex.zep.c" role="src" />
   <file baseinstalldir="/" md5sum="aedb58d2525a40aafab4d9c6d777451a" name="ice/validation/validator/regex.zep.h" role="src" />
   <file baseinstalldir="/" md5sum="190eea6b98d5c5670be19bfde16e3caa" name="ice/validation/validator/required.zep.c" role="src" />
   <file baseinstalldir="/" md5sum="66e6696b41808d91f3855b2f5bd362be" name="ice/validation/validator/required.zep.h" role="src" />
   <file baseinstalldir="/" md5sum="90ac15a7cd54927f526c32acbba0e10f" name="ice/validation/validator/same.zep.c" role="src" />
   <file baseinstalldir="/" md5sum="bea2b8f0a7e043badf12494c9f1df6c7" name="ice/validation/validator/same.zep.h" role="src" />
   <file baseinstalldir="/" md5sum="e17c697e175ea42a924db41fe564eb82" name="ice/validation/validator/unique.zep.c" role="src" />
   <file baseinstalldir="/" md5sum="e645eef05522229db1ab71ca71fa06c6" name="ice/validation/validator/unique.zep.h" role="src" />
   <file baseinstalldir="/" md5sum="cb5ec8427a35d6ecfa485ac6f768b3af" name="ice/validation/validator/url.zep.c" role="src" />
   <file baseinstalldir="/" md5sum="57ad615e63e5c9d60ba7c30ea465a25c" name="ice/validation/validator/url.zep.h" role="src" />
   <file baseinstalldir="/" md5sum="35504c95a92a609d7bf3416b77ea1f54" name="ice/validation/validator/with.zep.c" role="src" />
   <file baseinstalldir="/" md5sum="4144c2dd858d9290b4f84ce036d6af67" name="ice/validation/validator/with.zep.h" role="src" />
   <file baseinstalldir="/" md5sum="59a1e25e6f67dd6060bfaea3ef15ff8c" name="ice/validation/validator/without.zep.c" role="src" />
   <file baseinstalldir="/" md5sum="d4966fc68fd2953d89cb5d5398c13ebc" name="ice/validation/validator/without.zep.h" role="src" />
   <file baseinstalldir="/" md5sum="be49f36bc45bce8ce58397a0cf3ad019" name="kernel/array.c" role="src" />
   <file baseinstalldir="/" md5sum="00ef53d06d61c0690d7a6570ad3d01b7" name="kernel/array.h" role="src" />
   <file baseinstalldir="/" md5sum="79c2dd96773ed311ec6f2dfb5f300c0c" name="kernel/backtrace.c" role="src" />
   <file baseinstalldir="/" md5sum="552155f54be64bebb612339de3f70802" name="kernel/backtrace.h" role="src" />
   <file baseinstalldir="/" md5sum="2ca4af6999093805e0e35588d436f4fb" name="kernel/concat.c" role="src" />
   <file baseinstalldir="/" md5sum="153ed8dc6ec9046269d8e33f911f3ba2" name="kernel/concat.h" role="src" />
   <file baseinstalldir="/" md5sum="1a153347c13caf9060f56ab4bbd8f74e" name="kernel/debug.c" role="src" />
   <file baseinstalldir="/" md5sum="bfe383b48c965a972ab32bfd7c5f1761" name="kernel/debug.h" role="src" />
   <file baseinstalldir="/" md5sum="a151ed2794f31c8b8fb513fb0f718994" name="kernel/exception.c" role="src" />
   <file baseinstalldir="/" md5sum="1b168ddfedfa530a45b1906e1a1d80c1" name="kernel/exception.h" role="src" />
   <file baseinstalldir="/" md5sum="680f8c7a54e2ac2c19bf594bcd39c602" name="kernel/exit.c" role="src" />
   <file baseinstalldir="/" md5sum="7a7c20445c2d95f8f04ebe4e9df9d8eb" name="kernel/exit.h" role="src" />
   <file baseinstalldir="/" md5sum="42b581a56d2d420681b9a7a566452384" name="kernel/fcall.c" role="src" />
   <file baseinstalldir="/" md5sum="ef60b5149de1e3727d7da9077ca6bbc6" name="kernel/fcall.h" role="src" />
   <file baseinstalldir="/" md5sum="c2737684147543990e7202978d83183b" name="kernel/fcall_internal.h" role="src" />
   <file baseinstalldir="/" md5sum="720a59b77cc75f226c56ee2889c86ad6" name="kernel/file.c" role="src" />
   <file baseinstalldir="/" md5sum="828ce96cda25fb8af8cad1388d31644b" name="kernel/file.h" role="src" />
   <file baseinstalldir="/" md5sum="55f4ebede4f925cc3e34c40c2a3bef10" name="kernel/filter.c" role="src" />
   <file baseinstalldir="/" md5sum="fe04bffaec087a13d946b4539510b00f" name="kernel/filter.h" role="src" />
   <file baseinstalldir="/" md5sum="72a8b2ef847ce93b3b0dfaa227aef380" name="kernel/globals.h" role="src" />
   <file baseinstalldir="/" md5sum="15cab828d3c21495c65224174726da44" name="kernel/iterator.c" role="src" />
   <file baseinstalldir="/" md5sum="29ab708f1b2021700e7cc8ccbdd64339" name="kernel/iterator.h" role="src" />
   <file baseinstalldir="/" md5sum="4acedfa8282061fb5151faec0de5b40a" name="kernel/main.c" role="src" />
   <file baseinstalldir="/" md5sum="7940991c8c1120b75dcce72cb187a77a" name="kernel/main.h" role="src" />
   <file baseinstalldir="/" md5sum="2c2e672019e0b64a98d7a90e2d8ff546" name="kernel/math.c" role="src" />
   <file baseinstalldir="/" md5sum="51be5fbe2abbc5bb50b77ec865a0a0a5" name="kernel/math.h" role="src" />
   <file baseinstalldir="/" md5sum="c8caa298f2fb598e548f5ab524f183d9" name="kernel/memory.c" role="src" />
   <file baseinstalldir="/" md5sum="4e3efd641d0b8e4d8a6b4904e65a8e98" name="kernel/memory.h" role="src" />
   <file baseinstalldir="/" md5sum="f51a24022774c079e5b1d3fbc8d50311" name="kernel/object.c" role="src" />
   <file baseinstalldir="/" md5sum="1ec3543a9996507ebf65789cc1f4f4e2" name="kernel/object.h" role="src" />
   <file baseinstalldir="/" md5sum="481c05d6c9d799a3884b4ea359c58b89" name="kernel/operators.c" role="src" />
   <file baseinstalldir="/" md5sum="af334679cd0629101dd1427dd4e0feb5" name="kernel/operators.h" role="src" />
   <file baseinstalldir="/" md5sum="41e95ba29c5c16bee120589729b1135e" name="kernel/require.c" role="src" />
   <file baseinstalldir="/" md5sum="babaf6097c7163ee80b76bcaba74b1dd" name="kernel/require.h" role="src" />
   <file baseinstalldir="/" md5sum="94394ec908e5a1aac15bb78b1efe44cf" name="kernel/string.c" role="src" />
   <file baseinstalldir="/" md5sum="e0266649b7b70c339357924487eea970" name="kernel/string.h" role="src" />
   <file baseinstalldir="/" md5sum="8ff0fa9c352cec8626206e8485129efb" name="kernel/time.c" role="src" />
   <file baseinstalldir="/" md5sum="66bf922e8c0e2a438ca95aa8f69fb9d9" name="kernel/time.h" role="src" />
   <file baseinstalldir="/" md5sum="9e8d518e7bebdad784345f55e7034d3c" name="kernel/variables.c" role="src" />
   <file baseinstalldir="/" md5sum="c42aeca48580e38994a4cb09ecfc2d77" name="kernel/variables.h" role="src" />
   <file baseinstalldir="/" md5sum="f4715664c186c48c5dd9c5e697ec2f63" name="config.m4" role="src" />
   <file baseinstalldir="/" md5sum="6ab3d9872d76c3e258e7bc9a61ab69f6" name="config.w32" role="src" />
   <file baseinstalldir="/" md5sum="6ce4be3d86205f652e9dca94645b12ac" name="CREDITS" role="doc" />
   <file baseinstalldir="/" md5sum="7ab1761bb201627be5b31e3dc1a0982b" name="ext.h" role="src" />
   <file baseinstalldir="/" md5sum="e4fc9b9616ec5802c672a59ee06a97f9" name="ext_config.h" role="src" />
   <file baseinstalldir="/" md5sum="f64bb67e0aa9d24c1accc917bcbd073e" name="ice.c" role="src" />
   <file baseinstalldir="/" md5sum="e5ed172e10274d84b0c1640196a22a86" name="ice.h" role="src" />
   <file baseinstalldir="/" md5sum="e439167a44c2c403405e1efd329058c2" name="LICENSE" role="doc" />
   <file baseinstalldir="/" md5sum="3ee3aabd4b782373e762a7fe97415efa" name="php_ext.h" role="src" />
   <file baseinstalldir="/" md5sum="9c90721ff724eb036ce1af1fd7875d33" name="php_ice.h" role="src" />
  </dir>
 </contents>
 <dependencies>
  <required>
   <php>
    <min>7.4.0</min>
   </php>
   <pearinstaller>
    <min>1.4.0</min>
   </pearinstaller>
  </required>
 </dependencies>
 <providesextension>ice</providesextension>
 <extsrcrelease />
 <changelog>
  <release>
   <version>
    <release>1.8.0alpha2</release>
    <api>1.8.0</api>
   </version>
   <stability>
    <release>alpha</release>
    <api>stable</api>
   </stability>
   <date>2021-02-12</date>
   <license uri="https://www.iceframework.org/license">BSD-3-Clause</license>
   <notes>
- PHP 7.1, drop support, update phpunit to v8
- Update zephir parser to 1.3.5
- Zephir, use zephir-php8 branch
- Pdo, fix associative array in order by
- PHP 7.2 and 7.3, drop support
- Tests, fix get related count and filter
- Version, remove hyphen fix #292
   </notes>
  </release>
 </changelog>
</package>
