<?xml version="1.0" encoding="UTF-8"?>
<package packagerversion="1.9.5" version="2.0" xmlns="http://pear.php.net/dtd/package-2.0" xmlns:tasks="http://pear.php.net/dtd/tasks-1.0" xmlns:xsi="http://www.w3.org/2001/XMLSchema-instance" xsi:schemaLocation="http://pear.php.net/dtd/tasks-1.0    http://pear.php.net/dtd/tasks-1.0.xsd    http://pear.php.net/dtd/package-2.0    http://pear.php.net/dtd/package-2.0.xsd">
 <name>ares</name>
 <channel>pecl.php.net</channel>
 <summary>Asynchronous Resolver</summary>
 <description>Binding for the ares (MIT) or c-ares (CURL) library.</description>
 <lead>
  <name>Michael Wallner</name>
  <user>mike</user>
  <email>mike@php.net</email>
  <active>yes</active>
 </lead>
 <date>2014-11-14</date>
 <time>07:37:17</time>
 <version>
  <release>0.8.0</release>
  <api>0.8.0</api>
 </version>
 <stability>
  <release>beta</release>
  <api>beta</api>
 </stability>
 <license>BSD, revised</license>
 <notes>
* Fixed bug #63131 (OSX support for PECL ares)
+ Added support for options and flags up to c-ares 1.10
+ Added ares_set_local_{dev,ip4,ip6} functions
+ Added support for AAAA answers
 </notes>
 <contents>
  <dir name="/">
   <file md5sum="0f04fe2b99696d0b3455015968b2e856" name="tests/001.phpt" role="test" />
   <file md5sum="f546a5625ac056e8f55e37575303b209" name="tests/002.phpt" role="test" />
   <file md5sum="f58b86a0583b661900623ac2fc84159b" name="tests/003.phpt" role="test" />
   <file md5sum="c277398c890d389c0ff20cc5147e7021" name="CREDITS" role="doc" />
   <file md5sum="d41d8cd98f00b204e9800998ecf8427e" name="EXPERIMENTAL" role="doc" />
   <file md5sum="b1be79f1d96d4094c4e0306ee9da77a5" name="LICENSE" role="doc" />
   <file md5sum="916ed4b33eb48f3df6c05371450bdcf5" name="config.m4" role="src" />
   <file md5sum="68a687fa8864ff3efb1a6b775046ddbe" name="php_ares.c" role="src" />
   <file md5sum="03b2d11c454a3acb3c1a8a93e272c1cf" name="php_ares.h" role="src" />
  </dir>
 </contents>
 <dependencies>
  <required>
   <php>
    <min>4.3</min>
    <max>6.0</max>
    <exclude>6.0.0</exclude>
   </php>
   <pearinstaller>
    <min>1.4.1</min>
   </pearinstaller>
  </required>
 </dependencies>
 <providesextension>ares</providesextension>
 <extsrcrelease>
  <configureoption default="yes" name="with-ares" prompt="whether to enable asynchronous resolver support" />
 </extsrcrelease>
</package>
