<?xml version="1.0" encoding="ISO-8859-1" ?>
<!DOCTYPE package SYSTEM "http://pear.php.net/dtd/package-1.0">
<package version="1.0">
  <name>huffman</name>
  <summary>Huffman compression is a lossless compression algorithm that is ideal for compressing textual data.</summary>
  <description>Huffman compression belongs into a family of algorithms with a variable codeword length. That means that individual symbols (characters in a text file for instance) are replaced by bit sequences that have a distinct length. So symbols that occur a lot in a file are given a short sequence while other that are used seldom get a longer bit sequence.</description>
  <maintainers>
    <maintainer>
      <user>mnx</user>
      <name>Markus Nix</name>
      <email>mnix@docuverse.de</email>
      <role>lead</role>
    </maintainer>
  </maintainers>
  <release>
    <version>0.2.0</version>
    <date>2004-08-26</date>
    <license>PHP</license>
    <state>stable</state>
    <notes>Fixed memory leak bug (Thanks to Marcin Gibula).</notes>
    <deps>
      <dep type="php" rel="ge" version="4.3.0"/>
    </deps>
    <configureoptions>
      <configureoption name="enable-huffman" default="autodetect" prompt="Enable HUFFMAN?"/>
    </configureoptions>
    <filelist>
      <file role="src" name="config.m4"/>
      <file role="src" name="config.w32"/>
      <file role="src" name="huffman.c"/>
      <file role="src" name="php_huffman.h"/>
      <file role="src" name="huffalgo.c"/>
      <file role="src" name="huffalgo.h"/>
      <file role="doc" name="CREDITS"/>
      <file role="doc" name="README"/>
      <file role="test" name="huffman.php"/>
      <file role="test" name="tests/001.phpt"/>
      <file role="test" name="examples/example_file.php"/>
      <file role="test" name="examples/example_memory.php"/>
      <file role="test" name="examples/example_encode_file.php"/>
      <file role="test" name="examples/example_decode_file.php"/>
      <file role="test" name="examples/sample_orig.txt"/>
    </filelist>
  </release>
</package>
